Workbook
Name TM1REBUILDOPTION: 0
Name TM1RPTDATARNG1: 'Category Sales'!$31:$43
Name TM1RPTDATARNG1: 'Performance Summary'!$35:$39
Name TM1RPTDATARNG1: 'Performance Summary by Month'!$40:$44
Name TM1RPTDATARNG1: 'Store Sales'!$37:$174
Name TM1RPTDATARNG2: 'Item Sales'!$33:$62
Name TM1RPTDATARNG3: 'Top 20'!$28:$47
Name TM1RPTDATARNG4: 'New Product YTD'!$32:$43
Name TM1RPTDATARNG5: 'New Product Launch Month'!$32:$32
Name TM1RPTDATARNGARPT1: 'Store Sales'!$192:$221
Name TM1RPTDATARNGARPT2: 'Performance Summary'!$71:$90
Name TM1RPTDATARNGARPT2: 'Performance Summary by Month'!$69:$88
Name TM1RPTFMTIDCOL: 'Category Sales'!$A$1:$A$8
Name TM1RPTFMTIDCOL: 'Item Sales'!$A$1:$A$9
Name TM1RPTFMTIDCOL: 'New Product Launch Month'!$A$1:$A$9
Name TM1RPTFMTIDCOL: 'New Product YTD'!$A$1:$A$9
Name TM1RPTFMTIDCOL: 'Performance Summary'!$A$1:$A$11
Name TM1RPTFMTIDCOL: 'Performance Summary by Month'!$A$1:$A$13
Name TM1RPTFMTIDCOL: 'Store Sales'!$A$1:$A$14
Name TM1RPTFMTIDCOL: 'Top 20'!$A$1:$A$9
Name TM1RPTFMTRNG: 'Category Sales'!$C$1:$AG$8
Name TM1RPTFMTRNG: 'Item Sales'!$B$1:$AH$9
Name TM1RPTFMTRNG: 'New Product Launch Month'!$B$1:$L$9
Name TM1RPTFMTRNG: 'New Product YTD'!$B$1:$L$9
Name TM1RPTFMTRNG: 'Performance Summary'!$C$1:$L$11
Name TM1RPTFMTRNG: 'Performance Summary by Month'!$C$1:$T$13
Name TM1RPTFMTRNG: 'Store Sales'!$D$1:$AG$14
Name TM1RPTFMTRNG: 'Top 20'!$D$1:$J$9

Sheet Master
A22: BRAND PERFORMANCE REPORT
A24: MERCI
A25: YTD 2025.M12

Sheet Performance Summary
A1: [Begin Format Range]
A2: =0 -> 0
A3: =1 -> 1
A4: =2 -> 2
A5: =3 -> 3
A6: D
A7: N
A8: G
A9: H
A10: J
A11: [End Format Range]
C12: Mecca:RPT Item Store Sales Monthly:1
C13: Mecca:RPT Item Store Sales Monthly:ARPT2
C15: MECCA BRANDS BRAND PERFORMANCE REPORT | L15: =D24 -> MERCI
C18: Currency | D18: Report AUD
C19: Company | D19: Mecca Concept Consolidated Excl Intl | I19: CUBE: | J19: Mecca:CTL Retail Calendar
C20: RPT Item Store Sales Monthly Measure | D20: Sales Incl GST | I20: Weeks in Month
C21: DCS | D21: All DCS
C22: Lifestage | D22: All Lifestage
C23: Item | D23: All Item
C24: Brand | D24: =Master!A24 -> MERCI
C25: Store | D25: Total Stores by Concept Excl Non Store
C26: YTD Period: | D26: =Master!A25 -> YTD 2025.M12 | F26: ="YTD "&(D27-1)&"."&RIGHT(D26,3) -> YTD 2024.M12 | G26: =MID(D26,5,8) -> 2025.M12 | H26: December
C27: Year | D27: =MID(D26,5,4) -> 2025
C28: YEAR TO DATE 5 YEAR PERFORMANCE SUMMARY | L28: =H26&" "&D27 -> December 2025
C30: YTD SALES PERFORMANCE SUMMARY
C31: BUSINESS | G31: =$D$27&" YTD" -> 2025 YTD | H31: PRIOR YEAR EQUIVALENT | I31: =$D$27-1 -> 2024 | J31: =$D$27-2 -> 2023 | K31: =$D$27-3 -> 2022 | L31: =$D$27-4 -> 2021
C32: # Weeks Elapsed | G32: 52 | I32: 52 | J32: 53 | K32: 52 | L32: 52
G33: =$D$26 -> YTD 2025.M12 | H33: =$D$26 -> YTD 2025.M12 | I33: =$D$27-1 -> 2024 | J33: =$D$27-2 -> 2023 | K33: =$D$27-3 -> 2022 | L33: =$D$27-4 -> 2021
G34: Actual | H34: LY Actual | I34: Actual | J34: Actual | K34: Actual | L34: Actual
A35: N | C35: COSMETICA | F35: AUD | G35: 775.78 | H35: 461.2 | I35: 461.2 | J35: -197.66 | K35: -100 | L35: 52.66
A36: N | C36: MAXIMA | F36: AUD | G36: 146572.96 | H36: 188381.39 | I36: 188381.39 | J36: 103774.35 | K36: 120417.57 | L36: 94302.88
A37: N | C37: MECCA | F37: AUD | G37: 280757.39 | H37: 270997.63 | I37: 270997.63 | J37: 111180.89 | K37: 120737.13 | L37: 82182.09
A38: N | C38: SIS | F38: AUD | G38: 6229.1 | H38: 10170.4 | I38: 10170.4 | J38: 5986.3 | K38: 7482.45 | L38: 4706.5
A39: N | C39: DIRECT | F39: AUD | G39: 99333.11 | H39: 79374.53 | I39: 79374.53 | J39: 58419.94 | K39: 45062.89 | L39: 34204.7
C42: CUBE: | D42: Mecca:RPT Item Store Sales Monthly
C43: Currency | D43: Report AUD
C44: Company | D44: Mecca Brands Consolidated
C45: Trading As | D45: All Trading As Excl SIGLINE
C46: DCS | D46: All DCS
C47: Lifestage | D47: All Lifestage
C48: Item | D48: All Item
C49: Brand | D49: 3MORE
C50: Store | D50: All Store
G53: =G33 -> YTD 2025.M12 | H53: =H33 -> YTD 2025.M12 | I53: =I33 -> 2024 | J53: =J33 -> 2023 | K53: =K33 -> 2022 | L53: =L33 -> 2021
G54: Actual | H54: LY Actual | I54: Actual | J54: Actual | K54: Actual | L54: Actual
A55: Sales Incl GST | C55: COMPANY TOTAL | F55: AUD | G55: 533668.34 | H55: 549385.15 | I55: 549385.15 | J55: 279163.82 | K55: 293600.04 | L55: 215448.83
A56: Comp Sales Incl GST | C56: COMPANY SAME STORE SALES | F56: AUD | G56: 479534.15 | H56: 492718.41 | I56: 491791.31 | J56: 269914.08 | K56: 282507.67 | L56: 120990.86
C57: AV. SALES PER WEEK | F57: AUD | G57: =G55/G$32 -> 10262.853 | H57: =H55/G$32 -> 10565.099 | I57: =I55/I$32 -> 10565.099 | J57: =J55/J$32 -> 5267.2419 | K57: =K55/K$32 -> 5646.1546 | L57: =L55/L$32 -> 4143.2467
A58: Units | C58: COMPANY TOTAL | F58: UNITS | G58: 46899 | H58: 62071 | I58: 62071 | J58: 39517 | K58: 42149 | L58: 29171
A59: Comp Units | C59: COMPANY SAME STORE SALES | F59: UNITS | G59: 42544 | H59: 55647 | I59: 55488 | J59: 38021 | K59: 40473 | L59: 16167
C60: AV. SALES PER WEEK | F60: UNITS | G60: =G58/G$32 -> 901.90385 | H60: =H58/G$32 -> 1193.6731 | I60: =I58/I$32 -> 1193.6731 | J60: =J58/J$32 -> 745.60377 | K60: =K58/K$32 -> 810.55769 | L60: =L58/L$32 -> 560.98077
A61: Total Sales Growth on LY % | C61: GROWTH ON LY ($ SALES) | F61: % | G61: -0.028607999 | H61: 0 | I61: 1.020005 | J61: -0.07190315 | K61: 0.36285612 | L61: -0.39332755
A62: Total Units Growth on LY % | C62: GROWTH ON LY (UNITS SOLD) | F62: % | G62: -0.24442977 | H62: 0 | I62: 0.61655859 | J62: -0.086713351 | K62: 0.44494344 | L62: -0.47710977
A63: Comp Sales Growth on LY % | C63: SAME STORE GROWTH ON LY ($ SALES) | F63: % | G63: -0.026758205 | H63: 0 | I63: 0.97848709 | J63: -0.074096256 | K63: 0.34467221 | L63: -0.42126544
A64: Comp Units Growth on LY % | C64: SAME STORE GROWTH ON LY (UNITS SOLD) | F64: % | G64: -0.23546642 | H64: 0 | I64: 0.59512448 | J64: -0.089317365 | K64: 0.42435333 | L64: -0.51006122
C66: YTD PERFORMANCE SUMMARY BY BUSINESS
C67: BUSINESS | G67: =$D$27&" YTD" -> 2025 YTD | H67: PRIOR YEAR EQUIVALENT | I67: =$D$27-1 -> 2024 | J67: =$D$27-2 -> 2023 | K67: =$D$27-3 -> 2022 | L67: =$D$27-4 -> 2021
C68: # Weeks Elapsed | G68: 52 | I68: 52 | J68: 53 | K68: 52 | L68: 52
G69: =$D$26 -> YTD 2025.M12 | H69: =$D$26 -> YTD 2025.M12 | I69: =$D$27-1 -> 2024 | J69: =$D$27-2 -> 2023 | K69: =$D$27-3 -> 2022 | L69: =$D$27-4 -> 2021
G70: Actual | H70: LY Actual | I70: Actual | J70: Actual | K70: Actual | L70: Actual
A71: G | C71: COSMETICA | D71: Total Store Sales | E71: =UPPER(D71) -> TOTAL STORE SALES | F71: =IF(D71="Total Growth on LY","%",IF(D71="Same Store Growth on LY","%","AUD")) -> AUD | G71: 775.78 | H71: 461.2 | I71: 461.2 | J71: -197.66 | K71: -100 | L71: 52.66
A72: N | C72: COSMETICA | D72: Same Store Sales | E72: =UPPER(D72) -> SAME STORE SALES | F72: =IF(D72="Total Growth on LY","%",IF(D72="Same Store Growth on LY","%","AUD")) -> AUD | G72: 775.78 | H72: 447.2 | I72: 461.2 | J72: -197.66 | K72: -100 | L72: 41.66
A73: J | C73: COSMETICA | D73: Total Growth on LY | E73: =UPPER(D73) -> TOTAL GROWTH ON LY | F73: =IF(D73="Total Growth on LY","%",IF(D73="Same Store Growth on LY","%","AUD")) -> % | G73: 0.6820902 | H73: 0 | I73: -3.3332996 | J73: 0.9766 | K73: -2.8989746 | L73: -0.98556723
A74: H | C74: COSMETICA | D74: Same Store Growth on LY | E74: =UPPER(D74) -> SAME STORE GROWTH ON LY | F74: =IF(D74="Total Growth on LY","%",IF(D74="Same Store Growth on LY","%","AUD")) -> % | G74: 0.73474955 | H74: 0 | I74: -3.2209381 | J74: 1.0806316 | K74: -3.0136931 | L74: -0.98558018
A75: G | C75: MAXIMA | D75: Total Store Sales | E75: =UPPER(D75) -> TOTAL STORE SALES | F75: =IF(D75="Total Growth on LY","%",IF(D75="Same Store Growth on LY","%","AUD")) -> AUD | G75: 146572.96 | H75: 188381.39 | I75: 188381.39 | J75: 103774.35 | K75: 120417.57 | L75: 94302.88
A76: N | C76: MAXIMA | D76: Same Store Sales | E76: =UPPER(D76) -> SAME STORE SALES | F76: =IF(D76="Total Growth on LY","%",IF(D76="Same Store Growth on LY","%","AUD")) -> AUD | G76: 146572.96 | H76: 145189.83 | I76: 188187.59 | J76: 103744.35 | K76: 120125.78 | L76: 59582.14
A77: J | C77: MAXIMA | D77: Total Growth on LY | E77: =UPPER(D77) -> TOTAL GROWTH ON LY | F77: =IF(D77="Total Growth on LY","%",IF(D77="Same Store Growth on LY","%","AUD")) -> % | G77: -0.22193503 | H77: 0 | I77: 0.87223153 | J77: -0.16071596 | K77: 0.27692357 | L77: -0.46232572
A78: H | C78: MAXIMA | D78: Same Store Growth on LY | E78: =UPPER(D78) -> SAME STORE GROWTH ON LY | F78: =IF(D78="Total Growth on LY","%",IF(D78="Same Store Growth on LY","%","AUD")) -> % | G78: 0.0095263559 | H78: 0 | I78: 1.2169609 | J78: -0.10205247 | K78: 0.32451841 | L78: -0.45844161
A79: G | C79: MECCA | D79: Total Store Sales | E79: =UPPER(D79) -> TOTAL STORE SALES | F79: =IF(D79="Total Growth on LY","%",IF(D79="Same Store Growth on LY","%","AUD")) -> AUD | G79: 280757.39 | H79: 270997.63 | I79: 270997.63 | J79: 111180.89 | K79: 120737.13 | L79: 82182.09
A80: N | C80: MECCA | D80: Same Store Sales | E80: =UPPER(D80) -> SAME STORE SALES | F80: =IF(D80="Total Growth on LY","%",IF(D80="Same Store Growth on LY","%","AUD")) -> AUD | G80: 226623.2 | H80: 259672.55 | I80: 213597.59 | J80: 101961.15 | K80: 110015.05 | L80: 41786.92
A81: J | C81: MECCA | D81: Total Growth on LY | E81: =UPPER(D81) -> TOTAL GROWTH ON LY | F81: =IF(D81="Total Growth on LY","%",IF(D81="Same Store Growth on LY","%","AUD")) -> % | G81: 0.036014189 | H81: 0 | I81: 1.50269 | J81: -0.10016868 | K81: 0.46947904 | L81: -0.15774619
A82: H | C82: MECCA | D82: Same Store Growth on LY | E82: =UPPER(D82) -> SAME STORE GROWTH ON LY | F82: =IF(D82="Total Growth on LY","%",IF(D82="Same Store Growth on LY","%","AUD")) -> % | G82: -0.12727318 | H82: 0 | I82: 1.1227512 | J82: -0.16829061 | K82: 0.36767803 | L82: -0.23291903
... A90: H | C90: DIRECT | D90: Same Store Growth on LY | E90: =UPPER(D90) -> SAME STORE GROWTH ON LY | F90: =IF(D90="Total Growth on LY","%",IF(D90="Same Store Growth on LY","%","AUD")) -> % | G90: 0.25144817 | H90: 0 | I90: 0.3823896 | J90: 0.26822098 | K90: 0.31744731 | L90: -0.50609816
C92: DEFINITIONS:
C93: 1. Total sales aggregate the actual sales that fell within the reporting period.
C94: 2. Same store sales excludes sales from stores opened or closed in the last 12 months to allow a fair comparison to the year prior - i.e. a store opened part way through Sep 2014 will not be included until Oct 2015 as this is the first full month of trade; a store closed in part way through Aug 2014 will not be included from Aug 2014 onwards.
C95: 3. Total growth on last year is calculated using the sales for the same reporting period last year
C96: 4. Sales from NZ stores are converted using 1 AUD to 1.075 NZD.
C97: 5. Same store growth on last year is calculated using the sales for the same reporting period last year excluding any stores that have been opened or closed in the last 12 months.
C98: 6. Brand lead time is calculated as the total number of days from the date the order was placed (i.e. date on the C3 purchase order) to the promised receipt date (i.e. date when the order is ready for collection).
C99: 7. Total lead time is calculated as the total number of days from the date the order was placed (i.e. date on the C3 purchase order) to the expected receipt date (i.e. date when the order arrives at C3 Warehouse).

Sheet Performance Summary by Month
A1: [Begin Format Range]
A2: =0 -> 0
A3: =1 -> 1
A4: =2 -> 2
A5: =3 -> 3
A6: D
A7: N
A8: G
A9: H
A10: J
A11: R
A12: S
A13: [End Format Range]
C14: Mecca:RPT Item Store Sales Monthly:1
C15: Mecca:RPT Item Store Sales Monthly:ARPT2
C17: MECCA BRANDS BRAND PERFORMANCE REPORT | T17: =D26 -> MERCI
C20: Currency | D20: Report AUD
C21: Company | D21: Mecca Concept Consolidated Excl Intl | I21: CUBE: | J21: Mecca:CTL Retail Calendar
C22: RPT Item Store Sales Monthly Measure | D22: Sales Incl GST | I22: Weeks in Month
C23: DCS | D23: All DCS
C24: Lifestage | D24: All Lifestage
C25: Item | D25: All Item
C26: Brand | D26: =Master!A24 -> MERCI
C27: Store | D27: Total Stores by Concept Excl Non Store
C28: YTD Period: | D28: =Master!A25 -> YTD 2025.M12 | F28: ="YTD "&(D29-1)&"."&RIGHT(D28,3) -> YTD 2024.M12 | G28: =MID(D28,5,8) -> 2025.M12 | H28: December
C29: Year | D29: =MID(D28,5,4) -> 2025
C30: YEAR TO DATE 5 YEAR PERFORMANCE SUMMARY | T30: =$H$28&" "&$D$29 -> December 2025
C32: YTD SALES PERFORMANCE SUMMARY
C33: YTD MONTH REF: | G33: 1 | H33: 1 | I33: 1 | J33: 1 | K33: 1 | L33: 1 | M33: 1 | N33: 1 | O33: 1 | P33: 1 | Q33: 1 | R33: 1 | S33: 1 | T33: 1
C34: BUSINESS | G34: JAN 2025 | H34: FEB 2025 | I34: MAR 2025 | J34: APR 2025 | K34: MAY 2025 | L34: JUN 2025 | M34: JUL 2025 | N34: AUG 2025 | O34: SEP 2025 | P34: OCT 2025 | Q34: NOV 2025 | R34: DEC 2025 | S34: ="YTD "&$D$29 -> YTD 2025 | T34: % Share
C35: Start Date | G35: 2024-12-29 | H35: 2025-01-26 | I35: 2025-02-23 | J35: 2025-03-30 | K35: 2025-04-27 | L35: 2025-05-25 | M35: 2025-06-29 | N35: 2025-07-27 | O35: 2025-08-24 | P35: 2025-09-28 | Q35: 2025-10-26 | R35: 2025-11-23
C36: End Date | G36: 2025-01-25 | H36: 2025-02-22 | I36: 2025-03-29 | J36: 2025-04-26 | K36: 2025-05-24 | L36: 2025-06-28 | M36: 2025-07-26 | N36: 2025-08-23 | O36: 2025-09-27 | P36: 2025-10-25 | Q36: 2025-11-22 | R36: 2025-12-27
C37: # Weeks Elapsed | G37: 4 | H37: 4 | I37: 5 | J37: 4 | K37: 4 | L37: 5 | M37: 4 | N37: 4 | O37: 5 | P37: 4 | Q37: 4 | R37: 5 | S37: 52
G38: =$D$29&".M01" -> 2025.M01 | H38: =$D$29&".M02" -> 2025.M02 | I38: =$D$29&".M03" -> 2025.M03 | J38: =$D$29&".M04" -> 2025.M04 | K38: =$D$29&".M05" -> 2025.M05 | L38: =$D$29&".M06" -> 2025.M06 | M38: =$D$29&".M07" -> 2025.M07 | N38: =$D$29&".M08" -> 2025.M08 | O38: =$D$29&".M09" -> 2025.M09 | P38: =$D$29&".M10" -> 2025.M10 | Q38: =$D$29&".M11" -> 2025.M11 | R38: =$D$29&".M12" -> 2025.M12 | S38: =$D$28 -> YTD 2025.M12 | T38: =$D$28 -> YTD 2025.M12
G39: Actual | H39: Actual | I39: Actual | J39: Actual | K39: Actual | L39: Actual | M39: Actual | N39: Actual | O39: Actual | P39: Actual | Q39: Actual | R39: Actual | S39: Actual | T39: % of Total Brand Sales
A40: R | C40: COSMETICA | F40: AUD | G40: 59 | H40: 91 | I40: 39 | J40: 61.92 | K40: 70 | L40: 117 | M40: 83.88 | N40: 67 | O40: 77.98 | P40: 42 | Q40: 0 | R40: 67 | S40: 775.78 | T40: 0.0014536744
A41: R | C41: MAXIMA | F41: AUD | G41: 17272.8 | H41: 14399.61 | I41: 14744.53 | J41: 14021.25 | K41: 10553.99 | L41: 13839.28 | M41: 12609.73 | N41: 10210.58 | O41: 10521.89 | P41: 6384.36 | Q41: 6462.7 | R41: 15552.24 | S41: 146572.96 | T41: 0.27465178
A42: R | C42: MECCA | F42: AUD | G42: 29761.58 | H42: 24532.76 | I42: 27571.46 | J42: 24013.93 | K42: 19009.59 | L42: 24582.28 | M42: 22441.35 | N42: 17962.7 | O42: 21366.55 | P42: 17165.58 | Q42: 15232.48 | R42: 37117.13 | S42: 280757.39 | T42: 0.52608965
A43: R | C43: SIS | F43: AUD | G43: 983 | H43: 798.7 | I43: 998.4 | J43: 652.3 | K43: 637.5 | L43: 720.4 | M43: 557.8 | N43: 403.8 | O43: 262.2 | P43: 64 | Q43: 52 | R43: 99 | S43: 6229.1 | T43: 0.011672231
A44: S | C44: DIRECT | F44: AUD | G44: 7573 | H44: 6560.93 | I44: 6503.78 | J44: 5055.85 | K44: 7661.45 | L44: 5468.29 | M44: 11851.07 | N44: 8425.71 | O44: 8077.2 | P44: 9845.35 | Q44: 8475.76 | R44: 13834.72 | S44: 99333.11 | T44: 0.18613266
C47: CUBE: | D47: ="Mecca:RPT Item Store Sales Monthly" -> Mecca:RPT Item Store Sales Monthly
C48: Trading As | D48: All Trading As Excl SIGLINE
G51: =G38 -> 2025.M01 | H51: =H38 -> 2025.M02 | I51: =I38 -> 2025.M03 | J51: =J38 -> 2025.M04 | K51: =K38 -> 2025.M05 | L51: =L38 -> 2025.M06 | M51: =M38 -> 2025.M07 | N51: =N38 -> 2025.M08 | ... S51: =S38 -> YTD 2025.M12
G52: Actual | H52: Actual | I52: Actual | J52: Actual | K52: Actual | L52: Actual | M52: Actual | N52: Actual | O52: Actual | P52: Actual | Q52: Actual | R52: Actual | S52: Actual
A53: Sales Incl GST | C53: COMPANY TOTAL | F53: AUD | G53: 55649.38 | H53: 46383 | I53: 49857.17 | J53: 43805.25 | K53: 37932.53 | L53: 44727.25 | M53: 47543.83 | N53: 37069.79 | O53: 40305.82 | P53: 33501.29 | Q53: 30222.94 | R53: 66670.09 | S53: 533668.34
A54: Comp Sales Incl GST | C54: COMPANY SAME STORE SALES | F54: AUD | G54: 49661.37 | H54: 41579.43 | I54: 44464.74 | J54: 39448.25 | K54: 35801.13 | L54: 40929.65 | M54: 43628.52 | N54: 33715.99 | O54: 35237.13 | P54: 29533.37 | Q54: 26656.5 | R54: 58878.07 | S54: 479534.15
C55: AV. SALES PER WEEK | F55: AUD | G55: =IF(G$33=1,(G53/G$37),0) -> 13912.345 | H55: =IF(H$33=1,(H53/H$37),0) -> 11595.75 | I55: =IF(I$33=1,(I53/I$37),0) -> 9971.434 | J55: =IF(J$33=1,(J53/J$37),0) -> 10951.312 | K55: =IF(K$33=1,(K53/K$37),0) -> 9483.1325 | L55: =IF(L$33=1,(L53/L$37),0) -> 8945.45 | M55: =IF(M$33=1,(M53/M$37),0) -> 11885.958 | N55: =IF(N$33=1,(N53/N$37),0) -> 9267.4475 | ... S55: =IF(S$33=1,(S53/S$37),0) -> 10262.853
A56: Units | C56: COMPANY TOTAL | F56: UNITS | G56: 6172 | H56: 5044 | I56: 5586 | J56: 4852 | K56: 3956 | L56: 4224 | M56: 3301 | N56: 2493 | O56: 2626 | P56: 2244 | Q56: 2021 | R56: 4380 | S56: 46899
A57: Comp Units | C57: COMPANY SAME STORE SALES | F57: UNITS | G57: 5574 | H57: 4557 | I57: 5058 | J57: 4414 | K57: 3752 | L57: 3886 | M57: 3057 | N57: 2251 | O57: 2287 | P57: 1994 | Q57: 1794 | R57: 3920 | S57: 42544
C58: AV. SALES PER WEEK | F58: UNITS | G58: =IF(G$33=1,(G56/G$37),0) -> 1543 | H58: =IF(H$33=1,(H56/H$37),0) -> 1261 | I58: =IF(I$33=1,(I56/I$37),0) -> 1117.2 | J58: =IF(J$33=1,(J56/J$37),0) -> 1213 | K58: =IF(K$33=1,(K56/K$37),0) -> 989 | L58: =IF(L$33=1,(L56/L$37),0) -> 844.8 | M58: =IF(M$33=1,(M56/M$37),0) -> 825.25 | N58: =IF(N$33=1,(N56/N$37),0) -> 623.25 | ... S58: =IF(S$33=1,(S56/S$37),0) -> 901.90385
A59: Total Sales Growth on LY % | C59: GROWTH ON LY ($ SALES) | F59: % | G59: 0.6227706 | H59: 0.51029493 | I59: 0.12380169 | J59: 0.19126192 | K59: 0.49579761 | L59: -0.073579271 | M59: -0.0072392198 | N59: -0.13735816 | O59: -0.29503248 | P59: -0.37109219 | Q59: -0.29832545 | R59: -0.21773217 | S59: -0.028607999
A60: Total Units Growth on LY % | C60: GROWTH ON LY (UNITS SOLD) | F60: % | G60: 0.2665709 | H60: 0.1375733 | I60: 0.14514145 | J60: 0.28291909 | K60: 0.50189825 | L60: -0.14992956 | M60: -0.32797231 | N60: -0.43302252 | O60: -0.54786501 | P60: -0.61933842 | Q60: -0.5982906 | R60: -0.58118187 | S60: -0.24442977
A61: Comp Sales Growth on LY % | C61: SAME STORE GROWTH ON LY ($ SALES) | F61: % | G61: 0.63247966 | H61: 0.54089201 | I61: 0.096410194 | J61: 0.21339133 | K61: 0.59322899 | L61: -0.018187082 | M61: 0.052498871 | N61: -0.13176963 | O61: -0.3229216 | P61: -0.37970691 | Q61: -0.31342025 | R61: -0.25775335 | S61: -0.026758205
A62: Comp Units Growth on LY % | C62: SAME STORE GROWTH ON LY (UNITS SOLD) | F62: % | G62: 0.3084507 | H62: 0.18610099 | I62: 0.13970257 | J62: 0.32433243 | K62: 0.61099184 | L62: -0.095437616 | M62: -0.28708022 | N62: -0.43837325 | O62: -0.56791989 | P62: -0.62206217 | Q62: -0.60406091 | R62: -0.59807239 | S62: -0.23546642
C64: YTD PERFORMANCE SUMMARY BY BUSINESS
C65: BUSINESS | G65: JAN 2025 | H65: FEB 2025 | I65: MAR 2025 | J65: APR 2025 | K65: MAY 2025 | L65: JUN 2025 | M65: JUL 2025 | N65: AUG 2025 | O65: SEP 2025 | P65: OCT 2025 | Q65: NOV 2025 | R65: DEC 2025 | S65: ="YTD "&$D$29 -> YTD 2025
C66: # Weeks Elapsed | G66: 4 | H66: 4 | I66: 5 | J66: 4 | K66: 4 | L66: 5 | M66: 4 | N66: 4 | O66: 5 | P66: 4 | Q66: 4 | R66: 5 | S66: 52
G67: =$D$29&".M01" -> 2025.M01 | H67: =$D$29&".M02" -> 2025.M02 | I67: =$D$29&".M03" -> 2025.M03 | J67: =$D$29&".M04" -> 2025.M04 | K67: =$D$29&".M05" -> 2025.M05 | L67: =$D$29&".M06" -> 2025.M06 | M67: =$D$29&".M07" -> 2025.M07 | N67: =$D$29&".M08" -> 2025.M08 | O67: =$D$29&".M09" -> 2025.M09 | P67: =$D$29&".M10" -> 2025.M10 | Q67: =$D$29&".M11" -> 2025.M11 | R67: =$D$29&".M12" -> 2025.M12 | S67: =D28 -> YTD 2025.M12
G68: Actual | H68: Actual | I68: Actual | J68: Actual | K68: Actual | L68: Actual | M68: Actual | N68: Actual | O68: Actual | P68: Actual | Q68: Actual | R68: Actual | S68: Actual
A69: G | C69: COSMETICA | D69: Total Store Sales | E69: =UPPER(D69) -> TOTAL STORE SALES | F69: =IF(D69="Total Growth on LY","%",IF(D69="Same Store Growth on LY","%","AUD")) -> AUD | G69: 59 | H69: 91 | I69: 39 | J69: 61.92 | K69: 70 | L69: 117 | M69: 83.88 | N69: 67 | O69: 77.98 | P69: 42 | Q69: 0 | R69: 67 | S69: 775.78
A70: N | C70: COSMETICA | D70: Same Store Sales | E70: =UPPER(D70) -> SAME STORE SALES | F70: =IF(D70="Total Growth on LY","%",IF(D70="Same Store Growth on LY","%","AUD")) -> AUD | G70: 59 | H70: 91 | I70: 39 | J70: 61.92 | K70: 70 | L70: 117 | M70: 83.88 | N70: 67 | O70: 77.98 | P70: 42 | Q70: 0 | R70: 67 | S70: 775.78
A71: J | C71: COSMETICA | D71: Total Growth on LY | E71: =UPPER(D71) -> TOTAL GROWTH ON LY | F71: =IF(D71="Total Growth on LY","%",IF(D71="Same Store Growth on LY","%","AUD")) -> % | G71: 1.4583333 | H71: 4.3529412 | I71: -0.4 | J71: -0.073053892 | K71: 4.3846154 | L71: 0.60714286 | M71: 0.2408284 | N71: 1.5769231 | O71: 2.7133333 | P71: -0.46153846 | Q71: 0 | R71: 5.7 | S71: 0.6820902
A72: H | C72: COSMETICA | D72: Same Store Growth on LY | E72: =UPPER(D72) -> SAME STORE GROWTH ON LY | F72: =IF(D72="Total Growth on LY","%",IF(D72="Same Store Growth on LY","%","AUD")) -> % | G72: 4.9 | H72: 4.3529412 | I72: -0.4 | J72: -0.073053892 | K72: 4.3846154 | L72: 0.60714286 | M72: 0.2408284 | N72: 1.5769231 | O72: 2.7133333 | P72: -0.46153846 | Q72: 0 | R72: 5.7 | S72: 0.73474955
A73: G | C73: MAXIMA | D73: Total Store Sales | E73: =UPPER(D73) -> TOTAL STORE SALES | F73: =IF(D73="Total Growth on LY","%",IF(D73="Same Store Growth on LY","%","AUD")) -> AUD | G73: 17272.8 | H73: 14399.61 | I73: 14744.53 | J73: 14021.25 | K73: 10553.99 | L73: 13839.28 | M73: 12609.73 | N73: 10210.58 | O73: 10521.89 | P73: 6384.36 | Q73: 6462.7 | R73: 15552.24 | S73: 146572.96
A74: N | C74: MAXIMA | D74: Same Store Sales | E74: =UPPER(D74) -> SAME STORE SALES | F74: =IF(D74="Total Growth on LY","%",IF(D74="Same Store Growth on LY","%","AUD")) -> AUD | G74: 17272.8 | H74: 14399.61 | I74: 14744.53 | J74: 14021.25 | K74: 10553.99 | L74: 13839.28 | M74: 12609.73 | N74: 10210.58 | O74: 10521.89 | P74: 6384.36 | Q74: 6462.7 | R74: 15552.24 | S74: 146572.96
A75: J | C75: MAXIMA | D75: Total Growth on LY | E75: =UPPER(D75) -> TOTAL GROWTH ON LY | F75: =IF(D75="Total Growth on LY","%",IF(D75="Same Store Growth on LY","%","AUD")) -> % | G75: 0.23429159 | H75: 0.3042428 | I75: -0.15797412 | J75: -0.034458229 | K75: 0.13553972 | L75: -0.15357898 | M75: -0.2208126 | N75: -0.3407357 | O75: -0.46330442 | P75: -0.6346596 | Q75: -0.47750322 | R75: -0.36650057 | S75: -0.22193503
A76: H | C76: MAXIMA | D76: Same Store Growth on LY | E76: =UPPER(D76) -> SAME STORE GROWTH ON LY | F76: =IF(D76="Total Growth on LY","%",IF(D76="Same Store Growth on LY","%","AUD")) -> % | G76: 0.62562939 | H76: 0.79515146 | I76: 0.037194582 | J76: 0.259065 | K76: 0.58476647 | L76: 0.2603908 | M76: 0.13474611 | N76: -0.1702655 | O76: -0.30675105 | P76: -0.51502325 | Q76: -0.38380935 | R76: -0.26995208 | S76: 0.0095263559
A77: G | C77: MECCA | D77: Total Store Sales | E77: =UPPER(D77) -> TOTAL STORE SALES | F77: =IF(D77="Total Growth on LY","%",IF(D77="Same Store Growth on LY","%","AUD")) -> AUD | G77: 29761.58 | H77: 24532.76 | I77: 27571.46 | J77: 24013.93 | K77: 19009.59 | L77: 24582.28 | M77: 22441.35 | N77: 17962.7 | O77: 21366.55 | P77: 17165.58 | Q77: 15232.48 | R77: 37117.13 | S77: 280757.39
A78: N | C78: MECCA | D78: Same Store Sales | E78: =UPPER(D78) -> SAME STORE SALES | F78: =IF(D78="Total Growth on LY","%",IF(D78="Same Store Growth on LY","%","AUD")) -> AUD | G78: 23773.57 | H78: 19729.19 | I78: 22179.03 | J78: 19656.93 | K78: 16878.19 | L78: 20784.68 | M78: 18526.04 | N78: 14608.9 | O78: 16297.86 | P78: 13197.66 | Q78: 11666.04 | R78: 29325.11 | S78: 226623.2
A79: J | C79: MECCA | D79: Total Growth on LY | E79: =UPPER(D79) -> TOTAL GROWTH ON LY | F79: =IF(D79="Total Growth on LY","%",IF(D79="Same Store Growth on LY","%","AUD")) -> % | G79: 0.97703283 | H79: 0.71432844 | I79: 0.37453736 | J79: 0.42925852 | K79: 0.69861793 | L79: 0.08308157 | M79: 0.0096232361 | N79: -0.1012642 | O79: -0.27453664 | P79: -0.36882479 | Q79: -0.30968518 | R79: -0.25701502 | S79: 0.036014189
A80: H | C80: MECCA | D80: Same Store Growth on LY | E80: =UPPER(D80) -> SAME STORE GROWTH ON LY | F80: =IF(D80="Total Growth on LY","%",IF(D80="Same Store Growth on LY","%","AUD")) -> % | G80: 0.63230013 | H80: 0.45041978 | I80: 0.13483597 | J80: 0.23429218 | K80: 0.54318972 | L80: -0.032145736 | M80: -0.11188899 | N80: -0.23229159 | O80: -0.43340328 | P80: -0.49974035 | Q80: -0.42554433 | R80: -0.39261103 | S80: -0.12727318
... A88: H | C88: DIRECT | D88: Same Store Growth on LY | E88: =UPPER(D88) -> SAME STORE GROWTH ON LY | F88: =IF(D88="Total Growth on LY","%",IF(D88="Same Store Growth on LY","%","AUD")) -> % | G88: 0.65037288 | H88: 0.42380984 | I88: 0.044341034 | J88: 0.045389789 | K88: 0.73684127 | L88: -0.30996622 | M88: 0.37081232 | N88: 0.25840822 | O88: 0.1295551 | P88: 0.27446577 | Q88: 0.10766448 | R88: 0.55280892 | S88: 0.25144817
C90: DEFINITIONS
C91: 1. Total sales aggregate the actual sales that fell within the reporting period.
C92: 2. Total growth on last year is calculated using the sales for the same reporting period last year
C93: 3. Sales from NZ stores are converted using 1 AUD to 1.075 NZD.
C94: 4. Same store growth on last year is calculated using the sales for the same reporting period last year excluding any stores that have been opened or closed in the last 12 months.

Sheet Category Sales
A1: [Begin Format Range]
A2: =0 -> 0
A3: =1 -> 1
A4: =2 -> 2
A5: =3 -> 3
A6: D
A7: N
A8: [End Format Range]
C9: Mecca:RPT Item Store Sales Monthly:1
C11: Currency | D11: Report AUD
C12: Company | D12: Mecca Concept Consolidated Excl Intl
C13: Sales Version | D13: Actual
C14: Trading As | D14: All Trading As Excl SIGLINE
C15: Lifestage | D15: All Lifestage
C16: Item | D16: All Item
C17: Brand | D17: =Master!$A$24 -> MERCI
C18: Store | D18: Total Stores by Concept Excl Non Store
C19: YTD Period | D19: =Master!$A$25 -> YTD 2025.M12 | E19: ="YTD "&(D20-1)&"."&RIGHT(D19,3) -> YTD 2024.M12 | F19: =MID(D19,5,8) -> 2025.M12 | G19: December
C20: Year | D20: =MID(D19,5,4) -> 2025
C22: MECCA BRANDS BRAND PERFORMANCE REPORT | AG22: =$D$17 -> MERCI
C23: YEAR TO DATE PRODUCT PERFORMANCE SUMMARY | AG23: =$G$19&" "&$D$20 -> December 2025
C25: YTD CATEGORY SALES (AUD)
C26: YTD MONTH REF: | D26: 1 | E26: 1 | F26: 1 | G26: 1 | H26: 1 | I26: 1 | J26: 1 | K26: 1 | L26: 1 | M26: 1 | N26: 1 | O26: 1 | P26: 1 | Q26: 1 | R26: 1 | S26: 1 | T26: 1 | U26: 1 | V26: 1 | W26: 1 | X26: 1 | Y26: 1 | Z26: 1 | AA26: 1
D27: =$D$20&".M01" -> 2025.M01 | E27: =$D$20&".M01" -> 2025.M01 | F27: =$D$20&".M02" -> 2025.M02 | G27: =$D$20&".M02" -> 2025.M02 | H27: =$D$20&".M03" -> 2025.M03 | I27: =$D$20&".M03" -> 2025.M03 | J27: =$D$20&".M04" -> 2025.M04 | K27: =$D$20&".M04" -> 2025.M04 | L27: =$D$20&".M05" -> 2025.M05 | M27: =$D$20&".M05" -> 2025.M05 | N27: =$D$20&".M06" -> 2025.M06 | O27: =$D$20&".M06" -> 2025.M06 | P27: =$D$20&".M07" -> 2025.M07 | Q27: =$D$20&".M07" -> 2025.M07 | R27: =$D$20&".M08" -> 2025.M08 | S27: =$D$20&".M08" -> 2025.M08 | T27: =$D$20&".M09" -> 2025.M09 | U27: =$D$20&".M09" -> 2025.M09 | V27: =$D$20&".M10" -> 2025.M10 | W27: =$D$20&".M10" -> 2025.M10 | X27: =$D$20&".M11" -> 2025.M11 | Y27: =$D$20&".M11" -> 2025.M11 | Z27: =$D$20&".M12" -> 2025.M12 | AA27: =$D$20&".M12" -> 2025.M12 | AB27: =$D$19 -> YTD 2025.M12 | AC27: =$D$19 -> YTD 2025.M12 | AD27: =$E$19 -> YTD 2024.M12 | AE27: =$E$19 -> YTD 2024.M12
D28: Total Store Sales | E28: % of Total Department Sales | F28: Total Store Sales | G28: % of Total Department Sales | H28: Total Store Sales | I28: % of Total Department Sales | J28: Total Store Sales | K28: % of Total Department Sales | L28: Total Store Sales | M28: % of Total Department Sales | N28: Total Store Sales | O28: % of Total Department Sales | P28: Total Store Sales | Q28: % of Total Department Sales | R28: Total Store Sales | S28: % of Total Department Sales | T28: Total Store Sales | U28: % of Total Department Sales | V28: Total Store Sales | W28: % of Total Department Sales | X28: Total Store Sales | Y28: % of Total Department Sales | Z28: Total Store Sales | AA28: % of Total Department Sales | AB28: Total Store Sales | AC28: % of Total Department Sales | AD28: Total Store Sales | AE28: % of Total Department Sales
C29: CATEGORY | D29: JAN 2025 | F29: FEB 2025 | H29: MAR 2025 | J29: APR 2025 | L29: MAY 2025 | N29: JUN 2025 | P29: JUL 2025 | R29: AUG 2025 | T29: SEP 2025 | V29: OCT 2025 | X29: NOV 2025 | Z29: DEC 2025 | AB29: =LEFT(AC27,8) -> YTD 2025 | AD29: =LEFT(AE27,8) -> YTD 2024 | AF29: CHANGE IN | AG29: CHANGE IN
D30: $ SALES | E30: % SALES | F30: $ SALES | G30: % SALES | H30: $ SALES | I30: % SALES | J30: $ SALES | K30: % SALES | L30: $ SALES | M30: % SALES | N30: $ SALES | O30: % SALES | P30: $ SALES | Q30: % SALES | R30: $ SALES | S30: % SALES | T30: $ SALES | U30: % SALES | V30: $ SALES | W30: % SALES | X30: $ SALES | Y30: % SALES | Z30: $ SALES | AA30: % SALES | AB30: $ SALES | AC30: % SALES | AD30: $ SALES | AE30: % SALES | AF30: % SHARE | AG30: SHARE GROWTH
A31: 2 | C31: Body - Bath & Body | D31: 51.68 | E31: 0.00092867162 | F31: 77.36 | G31: 0.0016678524 | H31: 64.68 | I31: 0.0012973059 | J31: 13 | K31: 0.00029676808 | L31: 0 | M31: 0 | N31: 0 | O31: 0 | P31: 6032.24 | Q31: 0.12687745 | R31: 2099.2 | S31: 0.056628322 | T31: 3244.94 | U31: 0.080507976 | V31: 2389.03 | W31: 0.071311582 | X31: 1557.72 | Y31: 0.051540982 | Z31: 3888.56 | AA31: 0.058325405 | AB31: 19418.41 | AC31: 0.036386663 | AD31: 492.1 | AE31: 0.00089572862 | AF31: =AC31-AE31 -> 0.035490934 | AG31: =IFERROR((AB31/AD31)-1,0) -> 38.460293
A32: 2 | C32: Body - Cleanser | D32: 0 | E32: 0 | F32: 0 | G32: 0 | H32: 0 | I32: 0 | J32: 0 | K32: 0 | L32: 0 | M32: 0 | N32: 0 | O32: 0 | P32: 0 | Q32: 0 | R32: 0 | S32: 0 | T32: 36 | U32: 0.00089317126 | V32: 1130.4 | W32: 0.033741984 | X32: 921.6 | Y32: 0.030493393 | Z32: 1759.2 | AA32: 0.026386645 | AB32: 3847.2 | AC32: 0.0072089718 | AD32: 0 | AE32: 0 | AF32: =AC32-AE32 -> 0.0072089718 | AG32: =IFERROR((AB32/AD32)-1,0) -> 0
A33: 2 | C33: Body - Personal Care | D33: 8252.32 | E33: 0.14829132 | F33: 8173.25 | G33: 0.17621219 | H33: 7413.91 | I33: 0.14870298 | J33: 5780.85 | K33: 0.13196706 | L33: 4638.6 | M33: 0.12228554 | N33: 5939.03 | O33: 0.13278326 | P33: 3807.13 | Q33: 0.080076216 | R33: 3806.39 | S33: 0.10268173 | T33: 2972.24 | U33: 0.073742204 | V33: 3128.31 | W33: 0.093378792 | X33: 3458.78 | Y33: 0.11444221 | Z33: 10392.72 | AA33: 0.1558828 | AB33: 67763.53 | AC33: 0.12697686 | AD33: 40740.99 | AE33: 0.074157429 | AF33: =AC33-AE33 -> 0.052819431 | AG33: =IFERROR((AB33/AD33)-1,0) -> 0.66327647
A34: 2 | C34: Body - Hand & Foot Care | D34: 19938.1 | E34: 0.35828072 | F34: 15628.99 | G34: 0.33695513 | H34: 17438.48 | I34: 0.34976875 | J34: 14503.3 | K34: 0.33108589 | L34: 10620.52 | M34: 0.27998449 | N34: 11821.2 | O34: 0.26429526 | P34: 5131.01 | Q34: 0.10792168 | R34: 2579.38 | S34: 0.069581727 | T34: 2652.4 | U34: 0.065806874 | V34: 1743.63 | W34: 0.052046653 | X34: 1026.45 | Y34: 0.033962613 | Z34: 2898.74 | AA34: 0.043478867 | AB34: 105982.2 | AC34: 0.19859188 | AD34: 223175.7 | AE34: 0.40622813 | AF34: =AC34-AE34 -> -0.20763624 | AG34: =IFERROR((AB34/AD34)-1,0) -> -0.52511765
A35: 2 | C35: Body - Body Packs & Sets | D35: 1366.74 | E35: 0.024559842 | F35: 1643.4 | G35: 0.035431085 | H35: 1951.14 | I35: 0.039134592 | J35: 1667.58 | K35: 0.03806804 | L35: 1856.43 | M35: 0.048940316 | N35: 2375.19 | O35: 0.053103868 | P35: 2675.73 | Q35: 0.056279227 | R35: 2064 | S35: 0.055678762 | T35: 3449.6 | U35: 0.085585655 | V35: 3183.4 | W35: 0.095023207 | X35: 4863.01 | Y35: 0.1609046 | Z35: 6103.57 | AA35: 0.091548849 | AB35: 33199.79 | AC35: 0.062210529 | AD35: 22530.77 | AE35: 0.041010883 | AF35: =AC35-AE35 -> 0.021199647 | AG35: =IFERROR((AB35/AD35)-1,0) -> 0.47353109
A36: 2 | C36: Body - Moisturiser | D36: 0 | E36: 0 | F36: 0 | G36: 0 | H36: 0 | I36: 0 | J36: 0 | K36: 0 | L36: 0 | M36: 0 | N36: 0 | O36: 0 | P36: 1005.25 | Q36: 0.021143648 | R36: 987.4 | S36: 0.026636245 | T36: 811.32 | U36: 0.020129103 | V36: 819.65 | W36: 0.024466222 | X36: 337.93 | Y36: 0.011181242 | Z36: 914.3 | AA36: 0.013713796 | AB36: 4875.85 | AC36: 0.0091364798 | AD36: 0 | AE36: 0 | AF36: =AC36-AE36 -> 0.0091364798 | AG36: =IFERROR((AB36/AD36)-1,0) -> 0
A37: 1 | C37: Body | D37: 29608.84 | E37: 0.53206055 | F37: 25523 | G37: 0.55026626 | H37: 26868.21 | I37: 0.53890363 | J37: 21964.73 | K37: 0.50141775 | L37: 17115.55 | M37: 0.45121035 | N37: 20135.42 | O37: 0.45018238 | P37: 18651.36 | Q37: 0.39229822 | R37: 11536.37 | S37: 0.31120678 | T37: 13166.5 | U37: 0.32666498 | V37: 12394.42 | W37: 0.36996844 | X37: 12165.49 | Y37: 0.40252504 | Z37: 25957.09 | AA37: 0.38933636 | AB37: 235086.98 | AC37: 0.44051139 | AD37: 286939.56 | AE37: 0.52229217 | AF37: =AC37-AE37 -> -0.08178078 | AG37: =IFERROR((AB37/AD37)-1,0) -> -0.18070907
A38: 2 | C38: Fragrance - Personal | D38: 0 | E38: 0 | F38: 0 | G38: 0 | H38: 0 | I38: 0 | J38: 0 | K38: 0 | L38: 0 | M38: 0 | N38: 0 | O38: 0 | P38: 6063.1 | Q38: 0.12752654 | R38: 4840.8 | S38: 0.13058612 | T38: 4558.82 | U38: 0.11310575 | V38: 2516.63 | W38: 0.075120391 | X38: 1871.3 | Y38: 0.061916544 | Z38: 6174.65 | AA38: 0.092614994 | AB38: 26025.3 | AC38: 0.048766805 | AD38: 0 | AE38: 0 | AF38: =AC38-AE38 -> 0.048766805 | AG38: =IFERROR((AB38/AD38)-1,0) -> 0
A39: 1 | C39: Fragrance | D39: 0 | E39: 0 | F39: 0 | G39: 0 | H39: 0 | I39: 0 | J39: 0 | K39: 0 | L39: 0 | M39: 0 | N39: 0 | O39: 0 | P39: 6063.1 | Q39: 0.12752654 | R39: 4840.8 | S39: 0.13058612 | T39: 4558.82 | U39: 0.11310575 | V39: 2516.63 | W39: 0.075120391 | X39: 1871.3 | Y39: 0.061916544 | Z39: 6174.65 | AA39: 0.092614994 | AB39: 26025.3 | AC39: 0.048766805 | AD39: 0 | AE39: 0 | AF39: =AC39-AE39 -> 0.048766805 | AG39: =IFERROR((AB39/AD39)-1,0) -> 0
A40: 2 | C40: Skincare - Skin Accessories | D40: 4541.58 | E40: 0.081610613 | F40: 959.6 | G40: 0.020688614 | H40: 288.4 | I40: 0.0057845241 | J40: 0 | K40: 0 | L40: 3996 | M40: 0.10534494 | N40: 4099.07 | O40: 0.091645921 | P40: 3598.69 | Q40: 0.075692051 | R40: 3472.88 | S40: 0.093684912 | T40: 5141.57 | U40: 0.12756396 | V40: 4704.59 | W40: 0.14043011 | X40: 3845.74 | Y40: 0.12724573 | Z40: 5591.05 | AA40: 0.083861444 | AB40: 40239.17 | AC40: 0.075401082 | AD40: 47935.35 | AE40: 0.087252722 | AF40: =AC40-AE40 -> -0.011851641 | AG40: =IFERROR((AB40/AD40)-1,0) -> -0.16055333
A41: 2 | C41: Skincare - Treatment | D41: 21498.96 | E41: 0.38632883 | F41: 19900.4 | G41: 0.42904512 | H41: 22700.56 | I41: 0.45531184 | J41: 21840.52 | K41: 0.49858225 | L41: 16820.98 | M41: 0.44344472 | N41: 20492.76 | O41: 0.4581717 | P41: 19230.68 | Q41: 0.40448319 | R41: 17219.74 | S41: 0.46452219 | T41: 17438.93 | U41: 0.43266531 | V41: 13885.65 | W41: 0.41448105 | X41: 12340.41 | Y41: 0.40831269 | Z41: 28947.3 | AA41: 0.4341872 | AB41: 232316.89 | AC41: 0.43532073 | AD41: 214510.24 | AE41: 0.39045511 | AF41: =AC41-AE41 -> 0.044865616 | AG41: =IFERROR((AB41/AD41)-1,0) -> 0.083010722
A42: 1 | C42: Skincare | D42: 26040.54 | E42: 0.46793945 | F42: 20860 | G42: 0.44973374 | H42: 22988.96 | I42: 0.46109637 | J42: 21840.52 | K42: 0.49858225 | L42: 20816.98 | M42: 0.54878965 | N42: 24591.83 | O42: 0.54981762 | P42: 22829.37 | Q42: 0.48017524 | R42: 20692.62 | S42: 0.5582071 | T42: 22580.5 | U42: 0.56022927 | V42: 18590.24 | W42: 0.55491117 | X42: 16186.15 | Y42: 0.53555842 | Z42: 34538.35 | AA42: 0.51804865 | AB42: 272556.06 | AC42: 0.51072181 | AD42: 262445.59 | AE42: 0.47770783 | AF42: =AC42-AE42 -> 0.033013975 | AG42: =IFERROR((AB42/AD42)-1,0) -> 0.038524061
A43: 0 | C43: Total DCS | D43: 55649.38 | E43: 1 | F43: 46383 | G43: 1 | H43: 49857.17 | I43: 1 | J43: 43805.25 | K43: 1 | L43: 37932.53 | M43: 1 | N43: 44727.25 | O43: 1 | P43: 47543.83 | Q43: 1 | R43: 37069.79 | S43: 1 | T43: 40305.82 | U43: 1 | V43: 33501.29 | W43: 1 | X43: 30222.94 | Y43: 1 | Z43: 66670.09 | AA43: 1 | AB43: 533668.34 | AC43: 1 | AD43: 549385.15 | AE43: 1 | AF43: =AC43-AE43 -> 0 | AG43: =IFERROR((AB43/AD43)-1,0) -> -0.028607999

Sheet Top 20
A1: [Begin Format Range]
A2: =0 -> 0
A3: =1 -> 1
A4: =2 -> 2
A5: =3 -> 3
A6: D
A7: N
A8: P
A9: [End Format Range]
D10: Mecca:RPT Item Store Sales Monthly:3
D11: Filter: | E11: Order(TOPCOUNT(Distinct({ }), 20, ([RPT Item Store Sales Monthly Measure].[Total Units Sold])), ([RPT Item Store Sales Monthly Measure].[Total Units Sold]), BDESC)
D12: Currency | E12: Report AUD
D13: Company | E13: Mecca Concept Consolidated Excl Intl
D14: Month | E14: =Master!A25 -> YTD 2025.M12 | H14: =MID(E14,5,8) -> 2025.M12 | I14: December
D15: Sales Version | E15: Actual | I15: =MID(E14,5,4) -> 2025
D16: Trading As | E16: All Trading As Excl SIGLINE
D17: Lifestage | E17: All Lifestage
D18: DCS | E18: All DCS
D19: Brand | E19: =Master!A24 -> MERCI
D20: Store | E20: Total Stores by Concept Excl Non Store
C22: MECCA BRANDSBRAND PERFORMANCE REPORT | J22: =E19 -> MERCI
C23: YEAR TO DATE TOP 20 ITEMS | J23: =$I$14&" "&$I$15 -> December 2025
C25: RANK | E25: PRODUCT DESCRIPTION | F25: VENDOR ITEM CODE | G25: TOTAL UNITS SOLD | H25: % UNITS SOLD | I25: TOTAL $ SALES (AUD) | J25: % SALES
G26: Total Units Sold | H26: % of Total Brand Units | I26: Total Store Sales | J26: % of Total Brand Sales
E27: TOP 20 ITEMS TOTAL | G27: =SUM($G$28:$G$103) -> 46252 | H27: =SUM($H$28:$H$103) -> 0.9862044 | I27: =SUM($I$28:$I$103) -> 517830.54 | J27: =SUM($J$28:$J$103) -> 0.97032277
A28: N | C28: =C27+1 -> 1 | D28: I-060352 | E28: SPOT PATCHES | F28: MH-PATCH-24-22 | G28: 17741 | H28: 0.37828099 | I28: 232316.89 | J28: 0.43532073
A29: N | C29: =C28+1 -> 2 | D29: I-040423 | E29: HAND CLEANSING FLOWER POWER | F29: MH-GEL-30-FP-EU-19 | G29: 6093 | H29: 0.12991748 | I29: 32407.09 | J29: 0.06072515
A30: N | C30: =C29+1 -> 3 | D30: I-040425 | E30: HAND CLEANSING UNICORN | F30: MH-GEL-30-UE-EU-19 | G30: 4165 | H30: 0.088807864 | I30: 21409.7 | J30: 0.040117988
A31: N | C31: =C30+1 -> 4 | D31: I-060353 | E31: BLOTTING PAPER | F31: MH-PM-50-22 | G31: 2737 | H31: 0.058359453 | I31: 40239.17 | J31: 0.075401082
A32: N | C32: =C31+1 -> 5 | D32: I-040426 | E32: HAND CLEANSING NAMASTE | F32: MH-GEL-30-NA-EU-19 | G32: 2348 | H32: 0.050065033 | I32: 11986.43 | J32: 0.022460448
A33: N | C33: =C32+1 -> 6 | D33: I-044748 | E33: HAND CLEANS GLITTER FEVER | F33: MH-GEL-30-GF-EU-19 | G33: 2297 | H33: 0.04897759 | I33: 12374.43 | J33: 0.023187491
A34: N | C34: =C33+1 -> 7 | D34: I-054934 | E34: GLITTER SET | F34: MH-KIT-GLI-20 | G34: 1910 | H34: 0.040725815 | I34: 31395.38 | J34: 0.058829385
A35: N | C35: =C34+1 -> 8 | D35: I-066437 | E35: DEODORANT MOON 55G | F35: MH-DEO-MOON-55 | G35: 1828 | H35: 0.038977377 | I35: 30243.22 | J35: 0.056670441
A36: N | C36: =C35+1 -> 9 | D36: I-040427 | E36: HAND CLEANSING HELLO SUN | F36: MH-GEL-30-HS-EU-19 | G36: 1794 | H36: 0.038252415 | I36: 9323.09 | J36: 0.01746982
A37: N | C37: =C36+1 -> 10 | D37: I-066438 | E37: DEODORANT SUN 55G | F37: MH-DEO-SUN-55 | G37: 1155 | H37: 0.024627391 | I37: 19445.75 | J37: 0.036437893
A38: N | C38: =C37+1 -> 11 | D38: I-066436 | E38: DEODORANT EARTH 55G | F38: MH-DEO-EARTH-55 | G38: 1073 | H38: 0.022878953 | I38: 18074.56 | J38: 0.033868526
A39: N | C39: =C38+1 -> 12 | D39: I-048194 | E39: CLEANSING SPRAY PURIFYING | F39: MH-SPRAY-50-PUR-US | G39: 557 | H39: 0.011876586 | I39: 9947.18 | J39: 0.018639254
... A47: P | C47: =C46+1 -> 20 | D47: I-075725 | E47: FRAGRANCE MIST SUN 100ML | F47: MH-BODYMIST-SU | G47: 207 | H47: 0.0044137402 | I47: 5827.71 | J47: 0.010920097

Sheet New Product Launch Month
A1: [Begin Format Range]
A2: =0 -> 0
A3: =1 -> 1
A4: =2 -> 2
A5: =3 -> 3
A6: D
A7: N
A8: P
A9: [End Format Range]
B10: Mecca:RPT Item Store Sales Monthly:5
B11: Filter Reference | C11: Order(Distinct({ }), ([RPT Item Store Sales Monthly Measure].[Total Units Sold]), BDESC)
B12: Currency | C12: Report AUD
B13: Company | C13: Mecca Concept Consolidated Excl Intl
B14: Month | C14: =Master!A25 -> YTD 2025.M12 | E14: =MID(C14,5,8) -> 2025.M12 | F14: December
B15: Sales Version | C15: Actual | F15: =MID(C14,5,4) -> 2025
B16: Trading As | C16: All Trading As Excl SIGLINE
B17: Lifestage | C17: All Lifestage
B18: DCS | C18: All DCS
B19: Brand | C19: =Master!A24 -> MERCI
B20: Store | C20: Total Stores by Concept Excl Non Store
F21: =C32
B22: ="{TM1FILTERBYPATTERN({FILTER({TM1DRILLDOWNMEMBER({[Item].[All Item]},ALL,RECURSIVE)},[Item].[Launch Month]='"&$E$14&"')}, "&"'I-*'"&")}" -> {TM1FILTERBYPATTERN({FILTER({TM1DRILLDOWNMEMBER({[Item].[All Item]},ALL,RECURSIVE)},[Item].[Launch Month]='2025.M12')}, 'I-*')}
E25: MECCA BRANDS BRAND PERFORMANCE REPORT | L25: =C19 -> MERCI
E26: NEW PRODUCT PERFORMANCE REPORT | L26: =$F$14&" "&$F$15 -> December 2025
E28: ="PERFORMANCE OF NEW ITEMS LAUNCHED IN "&UPPER(L26)&" (RANKED BY UNITS SOLD)" -> PERFORMANCE OF NEW ITEMS LAUNCHED IN DECEMBER 2025 (RANKED BY UNITS SOLD)
I29: Total Units Sold | J29: % of Total Brand Sales | K29: Total Store Sales | L29: % of Total Brand Units
E30: LAUNCH MONTH | F30: LAUNCH DATE | G30: VENDOR ITEM CODE | H30: ITEM DESCRIPTION | I30: TOTAL UNITS SOLD | J30: % UNITS SOLD | K30: TOTAL $ SALES (AUD) | L30: % SALES
H31: NEW ITEMS TOTAL | I31: =SUM($I$32:$I$222) -> 0 | J31: =SUM($J$32:$J$222) -> 0 | K31: =SUM($K$32:$GK$222) -> 0 | L31: =SUM($L$32:$L$222) -> 0
A32: P | F32: =C32

Sheet New Product YTD
A1: [Begin Format Range]
A2: =0 -> 0
A3: =1 -> 1
A4: =2 -> 2
A5: =3 -> 3
A6: D
A7: N
A8: P
A9: [End Format Range]
B10: Mecca:RPT Item Store Sales Monthly:4
B11: Filter Reference | C11: Order(Distinct({ }), ([RPT Item Store Sales Monthly Measure].[Total Units Sold]), BDESC)
B12: Currency | C12: Report AUD
B13: Company | C13: Mecca Concept Consolidated Excl Intl
B14: Month | C14: =Master!A25 -> YTD 2025.M12 | E14: =MID(C14,5,4) -> 2025 | F14: =MID(C14,5,8) -> 2025.M12 | G14: 0 | H14: December
B15: Sales Version | C15: Actual
B16: Trading As | C16: All Trading As Excl SIGLINE
B17: Lifestage | C17: All Lifestage
B18: DCS | C18: All DCS
B19: Brand | C19: =Master!A24 -> MERCI
B20: Store | C20: Total Stores by Concept Excl Non Store
B23: ="{TM1FILTERBYPATTERN({FILTER({TM1DRILLDOWNMEMBER({[Item].[All Item]},ALL,RECURSIVE)},[Item].[Launch Year]='"&$E$14&"')}, "&"'I-*'"&")}" -> {TM1FILTERBYPATTERN({FILTER({TM1DRILLDOWNMEMBER({[Item].[All Item]},ALL,RECURSIVE)},[Item].[Launch Year]='2025')}, 'I-*')}
E25: MECCA BRANDS BRAND PERFORMANCE REPORT | L25: =C19 -> MERCI
E26: NEW PRODUCT PERFORMANCE REPORT | L26: =$H$14&" "&$E$14 -> December 2025
E28: ="PERFORMANCE OF NEW ITEMS LAUNCHED YTD "&UPPER(L26)&" (RANKED BY UNITS SOLD)" -> PERFORMANCE OF NEW ITEMS LAUNCHED YTD DECEMBER 2025 (RANKED BY UNITS SOLD)
I29: Total Units Sold | J29: % of Total Brand Sales | K29: Total Store Sales | L29: % of Total Brand Units
E30: LAUNCH MONTH | F30: LAUNCH DATE | G30: VENDOR ITEM CODE | H30: ITEM DESCRIPTION | I30: TOTAL UNITS SOLD | J30: % UNITS SOLD | K30: TOTAL $ SALES (AUD) | L30: % SALES
H31: YTD NEW ITEMS TOTAL | I31: =SUM($I$32:$I$451) -> 2754 | J31: =SUM($J$32:$J$451) -> 0.10518938 | K31: =SUM($K$32:$K$451) -> 56136.24 | L31: =SUM($L$32:$L$451) -> 0.058721934
A32: N | B32: I-075721 | C32: 2025-07-01 | E32: JULY | F32: =C32 -> 2025-07-01 | G32: MH-BSERUM-90-BZ | H32: BIKINI ARMPITS SERUM 90ML | I32: 481 | J32: 0.025000396 | K32: 13341.92 | L32: 0.010256082
A33: N | B33: I-075723 | C33: 2025-06-26 | E33: JUNE | F33: =C33 -> 2025-06-26 | G33: MH-BODYMIST-MO | H33: FRAGRANCE MIST MOON 100ML | I33: 479 | J33: 0.02504683 | K33: 13366.7 | L33: 0.010213437
A34: N | B34: I-075728 | C34: 2025-09-30 | E34: OCTOBER | F34: =C34 -> 2025-09-30 | G34: MH-GEL-30-UE-US-19 | H34: N HAND SANITISER - UNICORN | I34: 403 | J34: 0.0045084181 | K34: 2406 | L34: 0.0085929338
A35: N | B35: I-075729 | C35: 2025-09-30 | E35: OCTOBER | F35: =C35 -> 2025-09-30 | G35: MH-GEL-30-NA-US-19 | H35: N HAND SANITISER - NAMASTE | I35: 293 | J35: 0.0032851865 | K35: 1753.2 | L35: 0.006247468
A36: N | B36: I-075724 | C36: 2025-06-26 | E36: JUNE | F36: =C36 -> 2025-06-26 | G36: MH-BODYMIST-EA | H36: FRAGRANCE MIST EARTH 100ML | I36: 243 | J36: 0.012799879 | K36: 6830.89 | L36: 0.0051813472
A37: N | B37: I-075727 | C37: 2025-09-30 | E37: OCTOBER | F37: =C37 -> 2025-09-30 | G37: MH-GEL-30-HS-US-19 | H37: N HAND SANITISER - HELLO SUN | I37: 241 | J37: 0.0027005537 | K37: 1441.2 | L37: 0.0051387023
A38: N | B38: I-075725 | C38: 2025-06-26 | E38: JUNE | F38: =C38 -> 2025-06-26 | G38: MH-BODYMIST-SU | H38: FRAGRANCE MIST SUN 100ML | I38: 207 | J38: 0.010920097 | K38: 5827.71 | L38: 0.0044137402
A39: N | B39: I-075719 | C39: 2025-06-26 | E39: JUNE | F39: =C39 -> 2025-06-26 | G39: MH-BSERUM-90-BB | H39: BODY SERUM BACK BUTT 90ML | I39: 174 | J39: 0.0091364798 | K39: 4875.85 | L39: 0.0037101004
A40: N | B40: I-075722 | C40: 2025-07-01 | E40: JULY | F40: =C40 -> 2025-07-01 | G40: MH-BSERUM-90-BH | H40: BOOBS HIPS SERUM 90ML | I40: 115 | J40: 0.0060400435 | K40: 3223.38 | L40: 0.0024520779
A41: N | B41: I-075720 | C41: 2025-07-01 | E41: JULY | F41: =C41 -> 2025-07-01 | G41: MH-BSERUM-90-KE | H41: KNEES ELBOWS SERUM 90ML | I41: 95 | J41: 0.0049588664 | K41: 2646.39 | L41: 0.0020256295
A42: N | B42: I-075730 | C42: 2025-09-30 | E42: OCTOBER | F42: =C42 -> 2025-09-30 | G42: MH-SPRAY-50-ENE-US | H42: N HAND SANITIZER SPRAY ENERG | I42: 22 | J42: 0.00078325801 | K42: 418 | L42: 0.00046909316
A43: P | B43: I-075726 | C43: 2025-09-30 | E43: OCTOBER | F43: =C43 -> 2025-09-30 | G43: MH-GEL-30-FP-US-19 | H43: N HAND SANITISER - FLOWER PO | I43: 1 | J43: 9.3691149e-06 | K43: 5 | L43: 2.1322416e-05

Sheet Operation Summary
C3: Sales Version | D3: ="Actual" -> Actual
C4: Currency | D4: ="Report AUD" -> Report AUD
C5: Company | D5: ="Mecca Concept Consolidated Excl Intl" -> Mecca Concept Consolidated Excl Intl
C6: Trading As | D6: ="All Trading As" -> All Trading As
C7: Store | D7: ="Total Stores by Concept Excl Non Store" -> Total Stores by Concept Excl Non Store
C8: Brands | D8: =Master!A24 -> MERCI
C9: DCS | D9: ="All DCS" -> All DCS
C10: Lifestage | D10: ="All Lifestage" -> All Lifestage
C11: Item | D11: ="All Item" -> All Item | E11: All I Items | F11: All Tester Items | G11: All Fulfillment Items
C12: Brand Currency | D12: EUR
C18: YTD Period: | D18: =Master!A25 -> YTD 2025.M12 | E18: =MID(D18,5,8) -> 2025.M12 | F18: 2025-12-27 | G18: ="YTD "&$F$18 -> YTD 2025-12-27 | H18: ="YTD "&(E19-1)&"."&RIGHT(D18,3) -> YTD 2024.M12 | I18: December
C19: Year | E19: =MID(D18,5,4) -> 2025
D20: All Calendar Day | E20: =$E$19&".M01" -> 2025.M01 | F20: =$E$19&".M02" -> 2025.M02 | G20: =$E$19&".M03" -> 2025.M03 | H20: =$E$19&".M04" -> 2025.M04 | I20: =$E$19&".M05" -> 2025.M05 | J20: =$E$19&".M06" -> 2025.M06 | K20: =$E$19&".M07" -> 2025.M07 | L20: =$E$19&".M08" -> 2025.M08 | M20: =$E$19&".M09" -> 2025.M09 | N20: =$E$19&".M10" -> 2025.M10 | O20: =$E$19&".M11" -> 2025.M11 | P20: =$E$19&".M12" -> 2025.M12 | Q20: =E19 -> 2025
D21: 2019 CAL | E21: =CONCATENATE($E$19,"-Jan") -> 2025-Jan | F21: =CONCATENATE($E$19,"-Feb") -> 2025-Feb | G21: =CONCATENATE($E$19,"-Mar") -> 2025-Mar | H21: =CONCATENATE($E$19,"-Apr") -> 2025-Apr | I21: =CONCATENATE($E$19,"-May") -> 2025-May | J21: =CONCATENATE($E$19,"-Jun") -> 2025-Jun | K21: =CONCATENATE($E$19,"-Jul") -> 2025-Jul | L21: =CONCATENATE($E$19,"-Aug") -> 2025-Aug | M21: =CONCATENATE($E$19,"-Sep") -> 2025-Sep | N21: =CONCATENATE($E$19,"-Oct") -> 2025-Oct | O21: =CONCATENATE($E$19,"-Nov") -> 2025-Nov | P21: =CONCATENATE($E$19,"-Dec") -> 2025-Dec | Q21: =$E$19 -> 2025
C23: MECCA BRANDS BRAND PERFORMANCE REPORT | P23: =$D$8 -> MERCI
C24: YEAR TO DATE OPERATIONAL PERFORMANCE SUMMARY | P24: =I18&" "&E19 -> December 2025
C27: Mecca:RPT Item Store Sales Monthly
C28: YTD MONTH REF: | E28: 1 | F28: 1 | G28: 1 | H28: 1 | I28: 1 | J28: 1 | K28: 1 | L28: 1 | M28: 1 | N28: 1 | O28: 1 | P28: 1 | Q28: 1
C29: Item Sales
E30: JAN 2025 | F30: FEB 2025 | G30: MAR 2025 | H30: APR 2025 | I30: MAY 2025 | J30: JUN 2025 | K30: JUL 2025 | L30: AUG 2025 | M30: SEP 2025 | N30: OCT 2025 | O30: NOV 2025 | P30: DEC 2025 | Q30: YTD TOTAL
A31: Sales Incl GST | C31: Total Sales ($ at Retail) | D31: AUD | E31: 55649.38 | F31: 46383 | G31: 49857.17 | H31: 43805.25 | I31: 37932.53 | J31: 44727.25 | K31: 47543.83 | L31: 37069.79 | M31: 40305.82 | N31: 33501.29 | O31: 30222.94 | P31: 66670.09 | Q31: 533668.34
C33: Mecca:RPT Item Orders
C35: CALENDAR YTD ORDERS AND FULFILMENT SUMMARY - LIVE
E36: JAN 2025 | F36: FEB 2025 | G36: MAR 2025 | H36: APR 2025 | I36: MAY 2025 | J36: JUN 2025 | K36: JUL 2025 | L36: AUG 2025 | M36: SEP 2025 | N36: OCT 2025 | O36: NOV 2025 | P36: DEC 2025 | Q36: YTD TOTAL
A37: Original Order Direct Cost | C37: ORDERED | D37: =D12 -> EUR | E37: 0 | F37: 8780.5 | G37: 0 | H37: 2787 | I37: 17544 | J37: 2040 | K37: 19452.25 | L37: 11889 | M37: 32515.28 | N37: 5343 | O37: 14704.4 | P37: 22310 | Q37: =SUM(E37:P37) -> 137365.43
A38: Accepted Order Direct Cost | C38: INVOICED | D38: =D12 -> EUR | E38: 0 | F38: 4825.5 | G38: 0 | H38: 2787 | I38: 11904 | J38: 2040 | K38: 4328.5 | L38: 7815 | M38: 26679.52 | N38: 5343 | O38: 13424.4 | P38: 0 | Q38: =SUM(E38:P38) -> 79146.92
C39: FULFILMENT RATE | D39: % | E39: =IF(E37=0,"N/A",IF(ISERROR(E38/E37),0,(E38/E37))) -> N/A | F39: =IF(F37=0,"N/A",IF(ISERROR(F38/F37),0,(F38/F37))) -> 0.54957007 | G39: =IF(G37=0,"N/A",IF(ISERROR(G38/G37),0,(G38/G37))) -> N/A | H39: =IF(H37=0,"N/A",IF(ISERROR(H38/H37),0,(H38/H37))) -> 1 | I39: =IF(I37=0,"N/A",IF(ISERROR(I38/I37),0,(I38/I37))) -> 0.67852257 | J39: =IF(J37=0,"N/A",IF(ISERROR(J38/J37),0,(J38/J37))) -> 1 | K39: =IF(K37=0,"N/A",IF(ISERROR(K38/K37),0,(K38/K37))) -> 0.22251925 | L39: =IF(L37=0,"N/A",IF(ISERROR(L38/L37),0,(L38/L37))) -> 0.65733031 | ... Q39: =IF(Q37=0,"N/A",IF(ISERROR(Q38/Q37),0,(Q38/Q37))) -> 0.57617786
E41: JAN 2025 | F41: FEB 2025 | G41: MAR 2025 | H41: APR 2025 | I41: MAY 2025 | J41: JUN 2025 | K41: JUL 2025 | L41: AUG 2025 | M41: SEP 2025 | N41: OCT 2025 | O41: NOV 2025 | P41: DEC 2025 | Q41: YTD TOTAL
A42: Original Order Quantity | C42: ORDERED | D42: UNITS | E42: 0 | F42: 4408 | G42: 0 | H42: 972 | I42: 8412 | J42: 844 | K42: 9223 | L42: 4852 | M42: 21822 | N42: 2616 | O42: 8432 | P42: 11288 | Q42: =SUM(E42:P42) -> 72869
A43: Accepted Order Quantity | C43: INVOICED | D43: UNITS | E43: 0 | F43: 2826 | G43: 0 | H43: 972 | I43: 6116 | J43: 844 | K43: 2014 | L43: 2524 | M43: 18832 | N43: 2616 | O43: 7792 | P43: 0 | Q43: =SUM(E43:P43) -> 44536
C44: FULFILMENT RATE | D44: % | E44: =IF(E42=0,"N/A",IF(ISERROR(E43/E42),0,(E43/E42))) -> N/A | F44: =IF(F42=0,"N/A",IF(ISERROR(F43/F42),0,(F43/F42))) -> 0.64110708 | G44: =IF(G42=0,"N/A",IF(ISERROR(G43/G42),0,(G43/G42))) -> N/A | H44: =IF(H42=0,"N/A",IF(ISERROR(H43/H42),0,(H43/H42))) -> 1 | I44: =IF(I42=0,"N/A",IF(ISERROR(I43/I42),0,(I43/I42))) -> 0.72705659 | J44: =IF(J42=0,"N/A",IF(ISERROR(J43/J42),0,(J43/J42))) -> 1 | K44: =IF(K42=0,"N/A",IF(ISERROR(K43/K42),0,(K43/K42))) -> 0.21836713 | L44: =IF(L42=0,"N/A",IF(ISERROR(L43/L42),0,(L43/L42))) -> 0.52019786 | ... Q44: =IF(Q42=0,"N/A",IF(ISERROR(Q43/Q42),0,(Q43/Q42))) -> 0.61117896
C46: NOTE: Due to timing differences between the original order being submitted and the order being invoiced, the fulfilment rate for the most recently completed period may not be representative of the final fulfilment rate for that period
C48: CALENDAR YTD ORDERS AND FULFILMENT SUMMARY - TESTERS
E49: JAN 2025 | F49: FEB 2025 | G49: MAR 2025 | H49: APR 2025 | I49: MAY 2025 | J49: JUN 2025 | K49: JUL 2025 | L49: AUG 2025 | M49: SEP 2025 | N49: OCT 2025 | O49: NOV 2025 | P49: DEC 2025 | Q49: YTD TOTAL
A50: Original Order Quantity | C50: ORDERED | D50: UNITS | E50: 0 | F50: 0 | G50: 0 | H50: 0 | I50: 0 | J50: 0 | K50: 0 | L50: 0 | M50: 0 | N50: 0 | O50: 0 | P50: 0 | Q50: =SUM(E50:P50) -> 0
A51: Accepted Order Quantity | C51: INVOICED | D51: UNITS | E51: 0 | F51: 0 | G51: 0 | H51: 0 | I51: 0 | J51: 0 | K51: 0 | L51: 0 | M51: 0 | N51: 0 | O51: 0 | P51: 0 | Q51: =SUM(E51:P51) -> 0
C52: FULFILMENT RATE | D52: % | E52: =IF(E50=0,"N/A",IF(ISERROR(E51/E50),0,(E51/E50))) -> N/A | F52: =IF(F50=0,"N/A",IF(ISERROR(F51/F50),0,(F51/F50))) -> N/A | G52: =IF(G50=0,"N/A",IF(ISERROR(G51/G50),0,(G51/G50))) -> N/A | H52: =IF(H50=0,"N/A",IF(ISERROR(H51/H50),0,(H51/H50))) -> N/A | I52: =IF(I50=0,"N/A",IF(ISERROR(I51/I50),0,(I51/I50))) -> N/A | J52: =IF(J50=0,"N/A",IF(ISERROR(J51/J50),0,(J51/J50))) -> N/A | K52: =IF(K50=0,"N/A",IF(ISERROR(K51/K50),0,(K51/K50))) -> N/A | L52: =IF(L50=0,"N/A",IF(ISERROR(L51/L50),0,(L51/L50))) -> N/A | ... Q52: =IF(Q50=0,"N/A",IF(ISERROR(Q51/Q50),0,(Q51/Q50))) -> N/A
A53: Accepted Order Quantity | C53: TOTAL INVOICED | D53: UNITS | E53: 0 | F53: 2826 | G53: 0 | H53: 972 | I53: 6116 | J53: 844 | K53: 2014 | L53: 2524 | M53: 18832 | N53: 2616 | O53: 7792 | P53: 0 | Q53: =SUM(E53:P53) -> 44536
C54: % TESTERS OF TOTAL INVOICED ITEMS | D54: % | E54: =IF(E51=0,"N/A",IF(ISERROR(E51/E53),0,(E51/E53))) -> N/A | F54: =IF(F51=0,"N/A",IF(ISERROR(F51/F53),0,(F51/F53))) -> N/A | G54: =IF(G51=0,"N/A",IF(ISERROR(G51/G53),0,(G51/G53))) -> N/A | H54: =IF(H51=0,"N/A",IF(ISERROR(H51/H53),0,(H51/H53))) -> N/A | I54: =IF(I51=0,"N/A",IF(ISERROR(I51/I53),0,(I51/I53))) -> N/A | J54: =IF(J51=0,"N/A",IF(ISERROR(J51/J53),0,(J51/J53))) -> N/A | K54: =IF(K51=0,"N/A",IF(ISERROR(K51/K53),0,(K51/K53))) -> N/A | L54: =IF(L51=0,"N/A",IF(ISERROR(L51/L53),0,(L51/L53))) -> N/A | ... Q54: =IF(Q51=0,"N/A",IF(ISERROR(Q51/Q53),0,(Q51/Q53))) -> N/A
C56: NOTE: 100% DIF brands will not have any testers fulfillment as live items will be converted to testers at the Mecca end
A58: Original Order Direct Cost | C58: Ordered | D58: Report AUD | E58: 0 | F58: 2475.1656 | G58: 12062.086 | H58: 4644.302 | I58: 18362.862 | J58: 15082.074 | K58: 33138.416 | L58: 21306.452 | M58: 58271.111 | N58: 8526.8817 | O58: 1048.3871 | P58: 66334.05 | Q58: =SUM(E58:P58) -> 241251.79
A59: Accepted Order Direct Cost | C59: TOTAL INVOICED | D59: Report AUD | E59: 0 | F59: 695.36424 | G59: 7293.8742 | H59: 4644.302 | I59: 12434.412 | J59: 11346.568 | K59: 7373.9353 | L59: 14005.376 | M59: 47812.76 | N59: 8526.8817 | O59: 1048.3871 | P59: 24058.065 | Q59: =SUM(E59:P59) -> 139239.93
E61: =E37/E84 -> 0 | F61: =F37/F84 -> 14537.252 | G61: =G37/G84 -> 0 | H61: =H37/H84 -> 4614.2384 | I61: =I37/I84 -> 29046.358
C62: Mecca:RPT Tester Consumption
C64: YTD TESTER CONSUMPTION SUMMARY
E65: JAN 2025 | F65: FEB 2025 | G65: MAR 2025 | H65: APR 2025 | I65: MAY 2025 | J65: JUN 2025 | K65: JUL 2025 | L65: AUG 2025 | M65: SEP 2025 | N65: OCT 2025 | O65: NOV 2025 | P65: DEC 2025 | Q65: YTD TOTAL
A66: Quantity | C66: TOTAL TESTER CONSUMED | D66: UNITS | E66: 5 | F66: 11 | G66: 6 | H66: 10 | I66: 8 | J66: 62 | K66: 64 | L66: 7 | M66: 8 | N66: 1 | O66: 3 | P66: 6 | Q66: =SUM(E66:P66) -> 191
A67: Consumption at Retail Price | C67: TOTAL TESTER CONSUMED ($ AT RETAIL) | D67: AUD | E67: 69 | F67: 169 | G67: 100 | H67: 117 | I67: 111 | J67: 1580 | K67: 1728 | L67: 153 | M67: 162 | N67: 17 | O67: 73 | P67: 128 | Q67: =SUM(E67:P67) -> 4407
C68: % OF TOTAL SALES | D68: % | E68: =IF(ISERROR(E67/E31),0,(E67/E31)) -> 0.001239906 | F68: =IF(ISERROR(F67/F31),0,(F67/F31)) -> 0.0036435763 | G68: =IF(ISERROR(G67/G31),0,(G67/G31)) -> 0.0020057296 | H68: =IF(ISERROR(H67/H31),0,(H67/H31)) -> 0.0026709127 | I68: =IF(ISERROR(I67/I31),0,(I67/I31)) -> 0.0029262483 | J68: =IF(ISERROR(J67/J31),0,(J67/J31)) -> 0.035325221 | K68: =IF(ISERROR(K67/K31),0,(K67/K31)) -> 0.03634541 | L68: =IF(ISERROR(L67/L31),0,(L67/L31)) -> 0.0041273501 | ... Q68: =IF(ISERROR(Q67/Q31),0,(Q67/Q31)) -> 0.0082579379
C70: NOTE: Tester consumption is the total of Testers provided to MECCA by the brand and Testers converted from Live at the MECCA end
C72: Mecca: INP Brand Claim | F72: Mecca: CTL Currency
C73: Profit Centre | D73: Total Stores | F73: Version: | G73: Working Forecast
C74: Brand Claim Category | D74: All Brand Claim Category
C75: Item | D75: All Item
C78: YTD BRAND CLAIMS SUBMITTED SUMMARY
E79: JAN 2025 | F79: FEB 2025 | G79: MAR 2025 | H79: APR 2025 | I79: MAY 2025 | J79: JUN 2025 | K79: JUL 2025 | L79: AUG 2025 | M79: SEP 2025 | N79: OCT 2025 | O79: NOV 2025 | P79: DEC 2025 | Q79: YTD TOTAL
A80: Actual Claim Quantity | C80: TOTAL CLAIMS SUBMITTED | D80: UNITS | E80: 49 | F80: 49 | G80: 38 | H80: 34 | I80: 27 | J80: 106 | K80: 107 | L80: 35 | M80: 32 | N80: 10 | O80: 43 | P80: 0 | Q80: 530
A81: Actual Claim Amount | C81: TOTAL CLAIMS SUBMITTED | D81: AUD | E81: 178.59706 | F81: 191.98675 | G81: 131.19205 | H81: 107.43377 | I81: 99.602649 | J81: 568.4106 | K81: 677.56272 | L81: 173.08244 | M81: 164.12186 | N81: 47.043011 | O81: 213.24373 | P81: 0 | Q81: 2552.2767
C82: % OF TOTAL ORDERED ITEMS | D82: % | E82: =IF(ISERROR(E81/E58),0,(E81/E58)) -> 0 | F82: =IF(ISERROR(F81/F58),0,(F81/F58)) -> 0.077565217 | G82: =IF(ISERROR(G81/G58),0,(G81/G58)) -> 0.010876398 | H82: =IF(ISERROR(H81/H58),0,(H81/H58)) -> 0.023132383 | I82: =IF(ISERROR(I81/I58),0,(I81/I58)) -> 0.0054241354 | J82: =IF(ISERROR(J81/J58),0,(J81/J58)) -> 0.037687827 | K82: =IF(ISERROR(K81/K58),0,(K81/K58)) -> 0.020446443 | L82: =IF(ISERROR(L81/L58),0,(L81/L58)) -> 0.0081234755 | ... Q82: =IF(ISERROR(Q81/Q58),0,(Q81/Q58)) -> 0.010579307
C83: % OF TOTAL INVOICED ITEMS | D83: % | E83: =IF(ISERROR(E81/E59),0,(E81/E59)) -> 0 | F83: =IF(ISERROR(F81/F59),0,(F81/F59)) -> 0.27609524 | G83: =IF(ISERROR(G81/G59),0,(G81/G59)) -> 0.017986608 | H83: =IF(ISERROR(H81/H59),0,(H81/H59)) -> 0.023132383 | I83: =IF(ISERROR(I81/I59),0,(I81/I59)) -> 0.0080102418 | J83: =IF(ISERROR(J81/J59),0,(J81/J59)) -> 0.050095376 | K83: =IF(ISERROR(K81/K59),0,(K81/K59)) -> 0.091886177 | L83: =IF(ISERROR(L81/L59),0,(L81/L59)) -> 0.012358285 | ... Q83: =IF(ISERROR(Q81/Q59),0,(Q81/Q59)) -> 0.018330063
A84: Exchange Rate | C84: FX Rate | E84: 0.613 | F84: 0.604 | G84: 0.604 | H84: 0.604 | I84: 0.604 | J84: 0.604 | K84: 0.558 | L84: 0.558 | M84: 0.558 | N84: 0.558 | O84: 0.558 | P84: 0.558
C86: NOTE: % of Ordered Items is the 'Total Claims Submitted' divided by Ordered Amount in AUD, converted from foreign currency using the FX rate above.
C88: QTR BRAND CLAIMS SUBMITTED SUMMARY
E89: Q1 | F89: Q2 | G89: Q3 | H89: Q4
C90: TOTAL CLAIMS SUBMITTED | D90: UNITS | E90: =SUM(E80:G80) -> 136 | F90: =SUM(H80:J80) -> 167 | G90: =SUM(K80:M80) -> 174 | H90: =SUM(N80:P80) -> 53
C91: TOTAL CLAIMS SUBMITTED | D91: AUD | E91: =SUM(E81:G81) -> 501.77587 | F91: =SUM(H81:J81) -> 775.44702 | G91: =SUM(K81:M81) -> 1014.767 | H91: =SUM(N81:P81) -> 260.28674
C92: % OF TOTAL ORDERED ITEMS | D92: % | E92: =IF(E91=0,"N/A",IF(ISERROR(E91/SUM(E58:G58)),0,(E91/SUM(E58:G58)))) -> 0.034516557 | F92: =IF(F91=0,"N/A",IF(ISERROR(F91/SUM(H58:J58)),0,(F91/SUM(H58:J58)))) -> 0.020358691 | G92: =IF(G91=0,"N/A",IF(ISERROR(G91/SUM(K58:M58)),0,(G91/SUM(K58:M58)))) -> 0.0090028676 | H92: =IF(H91=0,"N/A",IF(ISERROR(H91/SUM(N58:P58)),0,(H91/SUM(N58:P58)))) -> 0.0034289168
C93: % OF TOTAL INVOICED ITEMS | D93: % | E93: =IF(E91=0,"N/A",IF(ISERROR(E91/SUM(E59:G59)),0,(E91/SUM(E59:G59)))) -> 0.062806471 | F93: =IF(F91=0,"N/A",IF(ISERROR(F91/SUM(H59:J59)),0,(F91/SUM(H59:J59)))) -> 0.027280187 | G93: =IF(G91=0,"N/A",IF(ISERROR(G91/SUM(K59:M59)),0,(G91/SUM(K59:M59)))) -> 0.014665944 | H93: =IF(H91=0,"N/A",IF(ISERROR(H91/SUM(N59:P59)),0,(H91/SUM(N59:P59)))) -> 0.0077389516

Sheet Appendix
A22: APPENDIX

Sheet Item Sales
A1: [Begin Format Range]
A2: =0 -> 0
A3: =1 -> 1
A4: =2 -> 2
A5: =3 -> 3
A6: D
A7: N
A8: P
A9: [End Format Range]
B10: Mecca:RPT Item Store Sales Monthly:2
B11: Currency | D11: Report AUD | H11: CUBE: | I11: Mecca:CTL Retail Calendar
B12: Company | D12: Mecca Concept Consolidated Excl Intl | H12: CTL Retail Calendar Measure | I12: Weeks in Month
B13: Sales Version | D13: Actual
B14: Trading As | D14: All Trading As Excl SIGLINE
B15: Lifestage | D15: All Lifestage
B16: DCS | D16: All DCS
B17: Brand | D17: =Master!$A$24 -> MERCI
B18: Store | D18: Total Stores by Concept Excl Non Store
B19: YTD Period | D19: =Master!$A$25 -> YTD 2025.M12 | E19: ="YTD "&(D20-1)&"."&RIGHT(D19,3) -> YTD 2024.M12 | F19: =MID(D19,5,8) -> 2025.M12 | G19: December
B20: Year | D20: =MID(D19,5,4) -> 2025
B21: Filter Reference: | D21: Order(Distinct({ }), ([Month].[YTD 2025.M12],[RPT Item Store Sales Monthly Measure].[Total Units Sold]), BDESC)
D23: MECCA BRANDS BRAND PERFORMANCE REPORT | AH23: =D17 -> MERCI
D24: YEAR TO DATE PRODUCT PERFORMANCE BY ITEM | AH24: =G19&" "&D20 -> December 2025
D26: YTD SALES PERFORMANCE BY ITEM (RANKED BY UNITS SOLD)
D27: YTD MONTH REF: | G27: 1 | H27: 1 | I27: 1 | J27: 1 | K27: 1 | L27: 1 | M27: 1 | N27: 1 | O27: 1 | P27: 1 | Q27: 1 | R27: 1 | S27: 1 | T27: 1 | U27: 1 | V27: 1 | W27: 1 | X27: 1 | Y27: 1 | Z27: 1 | AA27: 1 | AB27: 1 | AC27: 1 | AD27: 1
G28: =$D$20&".M01" -> 2025.M01 | H28: =$D$20&".M01" -> 2025.M01 | I28: =$D$20&".M02" -> 2025.M02 | J28: =$D$20&".M02" -> 2025.M02 | K28: =$D$20&".M03" -> 2025.M03 | L28: =$D$20&".M03" -> 2025.M03 | M28: =$D$20&".M04" -> 2025.M04 | N28: =$D$20&".M04" -> 2025.M04 | O28: =$D$20&".M05" -> 2025.M05 | P28: =$D$20&".M05" -> 2025.M05 | Q28: =$D$20&".M06" -> 2025.M06 | R28: =$D$20&".M06" -> 2025.M06 | S28: =$D$20&".M07" -> 2025.M07 | T28: =$D$20&".M07" -> 2025.M07 | U28: =$D$20&".M08" -> 2025.M08 | V28: =$D$20&".M08" -> 2025.M08 | W28: =$D$20&".M09" -> 2025.M09 | X28: =$D$20&".M09" -> 2025.M09 | Y28: =$D$20&".M10" -> 2025.M10 | Z28: =$D$20&".M10" -> 2025.M10 | AA28: =$D$20&".M11" -> 2025.M11 | AB28: =$D$20&".M11" -> 2025.M11 | AC28: =$D$20&".M12" -> 2025.M12 | AD28: =$D$20&".M12" -> 2025.M12 | AE28: =$D$19 -> YTD 2025.M12 | AF28: =$D$19 -> YTD 2025.M12 | AG28: =$D$19 -> YTD 2025.M12 | AH28: =$D$19 -> YTD 2025.M12
G29: Total Units Sold | H29: Total Store Sales | I29: Total Units Sold | J29: Total Store Sales | K29: Total Units Sold | L29: Total Store Sales | M29: Total Units Sold | N29: Total Store Sales | O29: Total Units Sold | P29: Total Store Sales | Q29: Total Units Sold | R29: Total Store Sales | S29: Total Units Sold | T29: Total Store Sales | U29: Total Units Sold | V29: Total Store Sales | W29: Total Units Sold | X29: Total Store Sales | Y29: Total Units Sold | Z29: Total Store Sales | AA29: Total Units Sold | AB29: Total Store Sales | AC29: Total Units Sold | AD29: Total Store Sales | AE29: Total Units Sold | AF29: % of Total Brand Units | AG29: Total Store Sales | AH29: % of Total Brand Sales
D30: RANK | E30: PRODUCT DESCRIPTION | F30: VENDOR ITEM CODE | G30: JAN 2025 | I30: FEB 2025 | K30: MAR 2025 | M30: APR 2025 | O30: MAY 2025 | Q30: JUN 2025 | S30: JUL 2025 | U30: AUG 2025 | W30: SEP 2025 | Y30: OCT 2025 | AA30: NOV 2025 | AC30: DEC 2025 | AE30: =LEFT(AE28,8) -> YTD 2025
G31: 4 | I31: 4 | K31: 5 | M31: 4 | O31: 4 | Q31: 5 | S31: 4 | U31: 4 | W31: 5 | Y31: 4 | AA31: 4 | AC31: 5 | AE31: 52
G32: UNITS | H32: $SALES | I32: UNITS | J32: $SALES | K32: UNITS | L32: $SALES | M32: UNITS | N32: $SALES | O32: UNITS | P32: $SALES | Q32: UNITS | R32: $SALES | S32: UNITS | T32: $SALES | U32: UNITS | V32: $SALES | W32: UNITS | X32: $SALES | Y32: UNITS | Z32: $SALES | AA32: UNITS | AB32: $SALES | AC32: UNITS | AD32: $SALES | AE32: UNITS | AF32: % UNITS | AG32: $SALES | AH32: % SALES
A33: N | B33: I-060352 | D33: =D32+1 -> 1 | E33: SPOT PATCHES | F33: MH-PATCH-24-22 | G33: 1686 | H33: 21498.96 | I33: 1558 | J33: 19900.4 | K33: 1777 | L33: 22700.56 | M33: 1703 | N33: 21840.52 | O33: 1319 | P33: 16820.98 | Q33: 1593 | R33: 20492.76 | S33: 1485 | T33: 19230.68 | U33: 1329 | V33: 17219.74 | W33: 1306 | X33: 17438.93 | Y33: 1005 | Z33: 13885.65 | AA33: 892 | AB33: 12340.41 | AC33: 2088 | AD33: 28947.3 | AE33: 17741 | AF33: 0.37828099 | AG33: 232316.89 | AH33: 0.43532073
A34: N | B34: I-040423 | D34: =D33+1 -> 2 | E34: HAND CLEANSING FLOWER POWER | F34: MH-GEL-30-FP-EU-19 | G34: 1050 | H34: 5333.06 | I34: 882 | J34: 4438.21 | K34: 922 | L34: 4641.46 | M34: 911 | N34: 4613.66 | O34: 811 | P34: 4225.38 | Q34: 1013 | R34: 6111.78 | S34: 282 | T34: 1701.13 | U34: 109 | V34: 653.98 | W34: 88 | X34: 539.39 | Y34: 11 | Z34: 65.04 | AA34: 2 | AB34: 12 | AC34: 12 | AD34: 72 | AE34: 6093 | AF34: 0.12991748 | AG34: 32407.09 | AH34: 0.06072515
A35: N | B35: I-040425 | D35: =D34+1 -> 3 | E35: HAND CLEANSING UNICORN | F35: MH-GEL-30-UE-EU-19 | G35: 917 | H35: 4666.39 | I35: 706 | J35: 3566.93 | K35: 867 | L35: 4328.05 | M35: 779 | N35: 3928.94 | O35: 524 | P35: 2676.27 | Q35: 260 | R35: 1569.81 | S35: 73 | T35: 439.79 | U35: 34 | V35: 205.92 | W35: 4 | X35: 21.6 | Y35: 0 | Z35: 0 | AA35: 0 | AB35: 0 | AC35: 1 | AD35: 6 | AE35: 4165 | AF35: 0.088807864 | AG35: 21409.7 | AH35: 0.040117988
A36: N | B36: I-060353 | D36: =D35+1 -> 4 | E36: BLOTTING PAPER | F36: MH-PM-50-22 | G36: 325 | H36: 4541.58 | I36: 70 | J36: 959.6 | K36: 21 | L36: 288.4 | M36: 0 | N36: 0 | O36: 290 | P36: 3996 | Q36: 274 | R36: 4099.07 | S36: 242 | T36: 3598.69 | U36: 232 | V36: 3472.88 | W36: 345 | X36: 5141.57 | Y36: 313 | Z36: 4704.59 | AA36: 254 | AB36: 3845.74 | AC36: 371 | AD36: 5591.05 | AE36: 2737 | AF36: 0.058359453 | AG36: 40239.17 | AH36: 0.075401082
A37: N | B37: I-040426 | D37: =D36+1 -> 5 | E37: HAND CLEANSING NAMASTE | F37: MH-GEL-30-NA-EU-19 | G37: 715 | H37: 3634.18 | I37: 523 | J37: 2637.01 | K37: 626 | L37: 3151.75 | M37: 284 | N37: 1441.75 | O37: 89 | P37: 456.99 | Q37: 74 | R37: 445.5 | S37: 31 | T37: 185.17 | U37: 6 | V37: 33.6 | W37: 0 | X37: 0 | Y37: 1 | Z37: 6.48 | AA37: -1 | AB37: -6 | AC37: 0 | AD37: 0 | AE37: 2348 | AF37: 0.050065033 | AG37: 11986.43 | AH37: 0.022460448
A38: N | B38: I-044748 | D38: =D37+1 -> 6 | E38: HAND CLEANS GLITTER FEVER | F38: MH-GEL-30-GF-EU-19 | G38: 370 | H38: 1883.17 | I38: 253 | J38: 1273.93 | K38: 315 | L38: 1581.55 | M38: 320 | N38: 1618.37 | O38: 296 | P38: 1517.15 | Q38: 398 | R38: 2395.23 | S38: 195 | T38: 1187.79 | U38: 60 | V38: 368.15 | W38: 68 | X38: 419.01 | Y38: 8 | Z38: 48 | AA38: 4 | AB38: 24 | AC38: 10 | AD38: 58.08 | AE38: 2297 | AF38: 0.04897759 | AG38: 12374.43 | AH38: 0.023187491
A39: N | B39: I-054934 | D39: =D38+1 -> 7 | E39: GLITTER SET | F39: MH-KIT-GLI-20 | G39: 41 | H39: 656.74 | I39: 95 | J39: 1521.86 | K39: 121 | L39: 1924.37 | M39: 97 | N39: 1546.81 | O39: 102 | P39: 1616.43 | Q39: 141 | R39: 2251.81 | S39: 160 | T39: 2553.18 | U39: 127 | V39: 2024 | W39: 209 | X39: 3409.6 | Y39: 185 | Z39: 3097.4 | AA39: 282 | AB39: 4775.61 | AC39: 350 | AD39: 6017.57 | AE39: 1910 | AF39: 0.040725815 | AG39: 31395.38 | AH39: 0.058829385
A40: N | B40: I-066437 | D40: =D39+1 -> 8 | E40: DEODORANT MOON 55G | F40: MH-DEO-MOON-55 | G40: 269 | H40: 4328.29 | I40: 262 | J40: 4185.92 | K40: 234 | L40: 3742.64 | M40: 170 | N40: 2692.76 | O40: 143 | P40: 2331.15 | Q40: 122 | R40: 2212.23 | S40: 47 | T40: 855.49 | U40: 32 | V40: 567.32 | W40: 26 | X40: 445.94 | Y40: 106 | Z40: 1795.93 | AA40: 109 | AB40: 1856.64 | AC40: 308 | AD40: 5228.91 | AE40: 1828 | AF40: 0.038977377 | AG40: 30243.22 | AH40: 0.056670441
A41: N | B41: I-040427 | D41: =D40+1 -> 9 | E41: HAND CLEANSING HELLO SUN | F41: MH-GEL-30-HS-EU-19 | G41: 357 | H41: 1803.62 | I41: 322 | J41: 1630.42 | K41: 360 | L41: 1815.46 | M41: 314 | N41: 1582.59 | O41: 191 | P41: 983.06 | Q41: 102 | R41: 614.82 | S41: 57 | T41: 345.93 | U41: 26 | V41: 153.6 | W41: 41 | X41: 248.15 | Y41: 10 | Z41: 61.44 | AA41: 3 | AB41: 18 | AC41: 11 | AD41: 66 | AE41: 1794 | AF41: 0.038252415 | AG41: 9323.09 | AH41: 0.01746982
A42: N | B42: I-066438 | D42: =D41+1 -> 10 | E42: DEODORANT SUN 55G | F42: MH-DEO-SUN-55 | G42: 128 | H42: 2073.8 | I42: 130 | J42: 2104.71 | K42: 122 | L42: 1952.4 | M42: 98 | N42: 1537.04 | O42: 70 | P42: 1137.37 | Q42: 101 | R42: 1821.25 | S42: 76 | T42: 1357.97 | U42: 97 | V42: 1765.39 | W42: 96 | X42: 1678.78 | Y42: 54 | Z42: 923.22 | AA42: 41 | AB42: 678.92 | AC42: 142 | AD42: 2414.9 | AE42: 1155 | AF42: 0.024627391 | AG42: 19445.75 | AH42: 0.036437893
A43: N | B43: I-066436 | D43: =D42+1 -> 11 | E43: DEODORANT EARTH 55G | F43: MH-DEO-EARTH-55 | G43: 115 | H43: 1850.23 | I43: 116 | J43: 1882.62 | K43: 109 | L43: 1718.87 | M43: 97 | N43: 1551.05 | O43: 72 | P43: 1170.08 | Q43: 105 | R43: 1905.55 | S43: 90 | T43: 1593.67 | U43: 81 | V43: 1473.68 | W43: 48 | X43: 847.52 | Y43: 24 | Z43: 409.16 | AA43: 54 | AB43: 923.22 | AC43: 162 | AD43: 2748.91 | AE43: 1073 | AF43: 0.022878953 | AG43: 18074.56 | AH43: 0.033868526
A44: N | B44: I-048194 | D44: =D43+1 -> 12 | E44: CLEANSING SPRAY PURIFYING | F44: MH-SPRAY-50-PUR-US | G44: 42 | H44: 742.92 | I44: 47 | J44: 818.58 | K44: 54 | L44: 972.25 | M44: 39 | N44: 687.35 | O44: 18 | P44: 320.92 | Q44: 16 | R44: 293.18 | S44: 58 | T44: 1012.24 | U44: 58 | V44: 1006.47 | W44: 69 | X44: 1256.04 | Y44: 48 | Z44: 902.12 | AA44: 29 | AB44: 484.45 | AC44: 79 | AD44: 1450.66 | AE44: 557 | AF44: 0.011876586 | AG44: 9947.18 | AH44: 0.018639254
... A62: P | B62: I-075726 | D62: =D61+1 -> 30 | E62: N HAND SANITISER - FLOWER PO | F62: MH-GEL-30-FP-US-19 | G62: 0 | H62: 0 | I62: 0 | J62: 0 | K62: 0 | L62: 0 | M62: 1 | N62: 5 | O62: 0 | P62: 0 | Q62: 0 | R62: 0 | S62: 0 | T62: 0 | U62: 0 | V62: 0 | W62: 0 | X62: 0 | Y62: 0 | Z62: 0 | AA62: 0 | AB62: 0 | AC62: 0 | AD62: 0 | AE62: 1 | AF62: 2.1322416e-05 | AG62: 5 | AH62: 9.3691149e-06

Sheet Store Sales
A1: [Begin Format Range]
A2: =0 -> 0
A3: =1 -> 1
A4: =2 -> 2
A5: =3 -> 3
A6: D
A7: N
A8: A
A9: B
A10: C
A11: E
A12: F
A13: G
A14: [End Format Range]
D15: Mecca:RPT Item Store Sales Monthly:1
D17: Currency | E17: Report AUD | L17: CUBE: | M17: Mecca:CTL Retail Calendar
D18: Company | E18: Mecca Concept Consolidated Excl Intl | L18: CTL Retail Calendar Measure | M18: Weeks in Month
D19: Sales Version | E19: Actual
D20: Trading As | E20: All Trading As
D21: Lifestage | E21: All Lifestage
D22: DCS | E22: All DCS
D23: Brand | E23: =Master!A24 -> MERCI
D24: Item | E24: All Item
D25: YTD Period | E25: =Master!$A$25 -> YTD 2025.M12 | F25: ="YTD "&(E26-1)&"."&RIGHT(E25,3) -> YTD 2024.M12 | H25: =MID(E25,5,8) -> 2025.M12 | I25: December
D26: Year | E26: =MID(E25,5,4) -> 2025
D28: MECCA BRANDS BRAND PERFORMANCE REPORT | AF28: =E23 -> MERCI
D29: YTD STORE SALES PERFORMANCE REPORT | AF29: =$I$25&" "&$E$26 -> December 2025
H31: 1 | I31: 1 | J31: 1 | K31: 1 | L31: 1 | M31: 1 | N31: 1 | O31: 1 | P31: 1 | Q31: 1 | R31: 1 | S31: 1 | T31: 1 | U31: 1 | V31: 1 | W31: 1 | X31: 1 | Y31: 1 | Z31: 1 | AA31: 1 | AB31: 1 | AC31: 1 | AD31: 1 | AE31: 1
H32: =$E$26&".M01" -> 2025.M01 | I32: =$E$26&".M01" -> 2025.M01 | J32: =$E$26&".M02" -> 2025.M02 | K32: =$E$26&".M02" -> 2025.M02 | L32: =$E$26&".M03" -> 2025.M03 | M32: =$E$26&".M03" -> 2025.M03 | N32: =$E$26&".M04" -> 2025.M04 | O32: =$E$26&".M04" -> 2025.M04 | P32: =$E$26&".M05" -> 2025.M05 | Q32: =$E$26&".M05" -> 2025.M05 | R32: =$E$26&".M06" -> 2025.M06 | S32: =$E$26&".M06" -> 2025.M06 | T32: =$E$26&".M07" -> 2025.M07 | U32: =$E$26&".M07" -> 2025.M07 | V32: =$E$26&".M08" -> 2025.M08 | W32: =$E$26&".M08" -> 2025.M08 | X32: =$E$26&".M09" -> 2025.M09 | Y32: =$E$26&".M09" -> 2025.M09 | Z32: =$E$26&".M10" -> 2025.M10 | AA32: =$E$26&".M10" -> 2025.M10 | AB32: =$E$26&".M11" -> 2025.M11 | AC32: =$E$26&".M11" -> 2025.M11 | AD32: =$E$26&".M12" -> 2025.M12 | AE32: =$E$26&".M12" -> 2025.M12 | AF32: =$E$25 -> YTD 2025.M12 | AG32: =$E$25 -> YTD 2025.M12
H33: Total Store Sales | I33: Total Growth on LY | J33: Total Store Sales | K33: Total Growth on LY | L33: Total Store Sales | M33: Total Growth on LY | N33: Total Store Sales | O33: Total Growth on LY | P33: Total Store Sales | Q33: Total Growth on LY | R33: Total Store Sales | S33: Total Growth on LY | T33: Total Store Sales | U33: Total Growth on LY | V33: Total Store Sales | W33: Total Growth on LY | X33: Total Store Sales | Y33: Total Growth on LY | Z33: Total Store Sales | AA33: Total Growth on LY | AB33: Total Store Sales | AC33: Total Growth on LY | AD33: Total Store Sales | AE33: Total Growth on LY | AF33: Total Store Sales | AG33: Store % of Trading As Sales
H34: JAN 2025 | J34: FEB 2025 | L34: MAR 2025 | N34: APR 2025 | P34: MAY 2025 | R34: JUN 2025 | T34: JUL 2025 | V34: AUG 2025 | X34: SEP 2025 | Z34: OCT 2025 | AB34: NOV 2025 | AD34: DEC 2025 | AF34: =LEFT(AF32,8) -> YTD 2025
F35: # Weeks | H35: 4 | J35: 4 | L35: 5 | N35: 4 | P35: 4 | R35: 5 | T35: 4 | V35: 4 | X35: 5 | Z35: 4 | AB35: 4 | AD35: 5 | AF35: 52
H36: $ SALES | I36: % ON LY | J36: $ SALES | K36: % ON LY | L36: $ SALES | M36: % ON LY | N36: $ SALES | O36: % ON LY | P36: $ SALES | Q36: % ON LY | R36: $ SALES | S36: % ON LY | T36: $ SALES | U36: % ON LY | V36: $ SALES | W36: % ON LY | X36: $ SALES | Y36: % ON LY | Z36: $ SALES | AA36: % ON LY | AB36: $ SALES | AC36: % ON LY | AD36: $ SALES | AE36: % ON LY | AF36: $ SALES | AG36: % SHARE
A37: N | D37: M001 | E37: Cosmetica Toorak Rd | F37: =E37 -> Cosmetica Toorak Rd | H37: 0 | I37: 0 | J37: 0 | K37: 0 | L37: 0 | M37: 0 | N37: 0 | O37: 0 | P37: 0 | Q37: 0 | R37: 0 | S37: 0 | T37: 0 | U37: 0 | V37: 0 | W37: 0 | X37: 0 | Y37: -1 | Z37: 0 | AA37: 0 | AB37: 0 | AC37: 0 | AD37: 0 | AE37: 0 | AF37: 0 | AG37: 0
A38: N | D38: M004 | E38: Cosmetica Chadstone | F38: =E38 -> Cosmetica Chadstone | H38: 0 | I38: 0 | J38: 0 | K38: 0 | L38: 0 | M38: 0 | N38: 0 | O38: -1 | P38: 0 | Q38: 0 | R38: 0 | S38: 0 | T38: 0 | U38: 0 | V38: 0 | W38: 0 | X38: 0 | Y38: 0 | Z38: 0 | AA38: 0 | AB38: 0 | AC38: 0 | AD38: -17 | AE38: 0 | AF38: -17 | AG38: -3.1854991e-05
A39: N | D39: M008 | E39: Cosmetica Claremont | F39: =E39 -> Cosmetica Claremont | H39: -16 | I39: 0 | J39: 0 | K39: 0 | L39: 0 | M39: 0 | N39: 0 | O39: 0 | P39: 0 | Q39: 0 | R39: 0 | S39: 0 | T39: 0 | U39: 0 | V39: 0 | W39: 0 | X39: 0 | Y39: 0 | Z39: 0 | AA39: 0 | AB39: 0 | AC39: 0 | AD39: 0 | AE39: 0 | AF39: -16 | AG39: -2.9981168e-05
A40: N | D40: M013 | E40: Cosmetica Queens Plaza | F40: =E40 -> Cosmetica Queens Plaza | H40: 91 | I40: 0 | J40: 91 | K40: 6.5833333 | L40: 39 | M40: -0.4 | N40: 72.8 | O40: 0 | P40: 52 | Q40: 3 | R40: 130 | S40: 0.78571429 | T40: 52 | U40: -0.23076923 | V40: 52 | W40: 1 | X40: 53 | Y40: 0.35897436 | Z40: 42 | AA40: -0.46153846 | AB40: 0 | AC40: 0 | AD40: 84 | AE40: 2.2307692 | AF40: 758.8 | AG40: 0.0014218569
A41: N | D41: M020 | E41: Cosmetica Mosman | F41: =E41 -> Cosmetica Mosman | H41: 0 | I41: -1 | J41: 0 | K41: 0 | L41: 0 | M41: 0 | N41: 0 | O41: 0 | P41: 0 | Q41: 0 | R41: 0 | S41: 0 | T41: 0 | U41: 0 | V41: 0 | W41: 0 | X41: 0 | Y41: 0 | Z41: 0 | AA41: 0 | AB41: 0 | AC41: 0 | AD41: 0 | AE41: 0 | AF41: 0 | AG41: 0
A42: N | D42: M025 | E42: Cosmetica Armadale | F42: =E42 -> Cosmetica Armadale | H42: 0 | I42: 0 | J42: 0 | K42: 0 | L42: 0 | M42: 0 | N42: 0 | O42: 0 | P42: 0 | Q42: 0 | R42: 0 | S42: 0 | T42: 18 | U42: 0 | V42: 0 | W42: 0 | X42: 0 | Y42: 0 | Z42: 0 | AA42: 0 | AB42: 0 | AC42: 0 | AD42: 0 | AE42: 0 | AF42: 18 | AG42: 3.3728814e-05
A43: N | D43: M029 | E43: Cosmetica Carlton | F43: =E43 -> Cosmetica Carlton | H43: 0 | I43: 0 | J43: 0 | K43: 0 | L43: 0 | M43: 0 | N43: 0 | O43: 0 | P43: 18 | Q43: 0 | R43: 0 | S43: 0 | T43: 0 | U43: 0 | V43: 0 | W43: 0 | X43: 0 | Y43: 0 | Z43: 0 | AA43: 0 | AB43: 0 | AC43: 0 | AD43: 0 | AE43: 0 | AF43: 18 | AG43: 3.3728814e-05
A44: N | D44: M030 | E44: Cosmetica Camberwell | F44: =E44 -> Cosmetica Camberwell | H44: 0 | I44: 0 | J44: 0 | K44: 0 | L44: 0 | M44: 0 | N44: 0 | O44: 0 | P44: 0 | Q44: 0 | R44: 0 | S44: 0 | T44: 0 | U44: 0 | V44: 15 | W44: 0 | X44: 0 | Y44: 0 | Z44: 0 | AA44: 0 | AB44: 0 | AC44: 0 | AD44: 0 | AE44: -1 | AF44: 15 | AG44: 2.8107345e-05
A45: N | D45: M036 | E45: Cosmetica Miranda | F45: =E45 -> Cosmetica Miranda | H45: -16 | I45: 0 | J45: 0 | K45: 0 | L45: 0 | M45: 0 | N45: 0 | O45: 0 | P45: 0 | Q45: 0 | R45: 0 | S45: 0 | T45: 0 | U45: 0 | V45: 0 | W45: 0 | X45: 0 | Y45: 0 | Z45: 0 | AA45: 0 | AB45: 0 | AC45: 0 | AD45: 0 | AE45: 0 | AF45: -16 | AG45: -2.9981168e-05
A46: N | D46: M038 | E46: Cosmetica Pacific Fair | F46: =E46 -> Cosmetica Pacific Fair | H46: 0 | I46: -1 | J46: 0 | K46: -1 | L46: 0 | M46: 0 | N46: 0 | O46: 0 | P46: 0 | Q46: 0 | R46: -13 | S46: 0 | T46: 0 | U46: 0 | V46: 0 | W46: 0 | X46: 0 | Y46: 0 | Z46: 0 | AA46: 0 | AB46: 0 | AC46: 0 | AD46: 0 | AE46: 0 | AF46: -13 | AG46: -2.4359699e-05
A47: N | D47: M101 | E47: Cosmetica Ponsonby | F47: =E47 -> Cosmetica Ponsonby | H47: 0 | I47: 0 | J47: 0 | K47: 0 | L47: 0 | M47: 0 | N47: 0 | O47: 0 | P47: 0 | Q47: 0 | R47: 0 | S47: 0 | T47: 0 | U47: 0 | V47: 0 | W47: 0 | X47: 24.98 | Y47: 0 | Z47: 0 | AA47: 0 | AB47: 0 | AC47: 0 | AD47: 0 | AE47: 0 | AF47: 24.98 | AG47: 4.6808098e-05
A48: N | D48: M105 | E48: Cosmetica Takapuna | F48: =E48 -> Cosmetica Takapuna | H48: 0 | I48: 0 | J48: 0 | K48: 0 | L48: 0 | M48: 0 | N48: -10.88 | O48: 0 | P48: 0 | Q48: 0 | R48: 0 | S48: 0 | T48: 13.88 | U48: 0 | V48: 0 | W48: 0 | X48: 0 | Y48: 0 | Z48: 0 | AA48: 0 | AB48: 0 | AC48: 0 | AD48: 0 | AE48: 0 | AF48: 3 | AG48: 5.6214689e-06
A49: 1 | D49: Cosmetica Stores Brand | E49: Cosmetica Stores Brand | F49: =E49 -> Cosmetica Stores Brand | H49: 59 | I49: 1.4583333 | J49: 91 | K49: 4.3529412 | L49: 39 | M49: -0.4 | N49: 61.92 | O49: -0.073053892 | P49: 70 | Q49: 4.3846154 | R49: 117 | S49: 0.60714286 | T49: 83.88 | U49: 0.2408284 | V49: 67 | W49: 1.5769231 | X49: 77.98 | Y49: 2.7133333 | Z49: 42 | AA49: -0.46153846 | AB49: 0 | AC49: 0 | AD49: 67 | AE49: 5.7 | AF49: 775.78 | AG49: 0.0014536744
A50: N | D50: L001 | E50: Maxima Melbourne Central | F50: =E50 -> Maxima Melbourne Central | H50: 0 | I50: -1 | J50: 0 | K50: -1 | L50: 0 | M50: -1 | N50: 0 | O50: -1 | P50: 0 | Q50: -1 | R50: 0 | S50: -1 | T50: 0 | U50: -1 | V50: 0 | W50: -1 | X50: 0 | Y50: 0 | Z50: 0 | AA50: 0 | AB50: 0 | AC50: 0 | AD50: 0 | AE50: 0 | AF50: 0 | AG50: 0
A51: N | D51: L002 | E51: Maxima Wintergarden | F51: =E51 -> Maxima Wintergarden | H51: 1121.2 | I51: 0.19530917 | J51: 680 | K51: 0.33595285 | L51: 1395.8 | M51: 0.067941852 | N51: 1514.6 | O51: 1.0434431 | P51: 1338.6 | Q51: 0.96448488 | R51: 2057.4 | S51: 0.91814283 | T51: 1722.6 | U51: 1.1136196 | V51: 1586.8 | W51: 0.32653402 | X51: 1711.4 | Y51: 0.11101013 | Z51: 993.8 | AA51: -0.36213094 | AB51: 1241.4 | AC51: 0.64729299 | AD51: 2055.4 | AE51: 1.4067916 | AF51: 17419 | AG51: 0.032640123
A52: N | D52: L006 | E52: Maxima Warringah | F52: =E52 -> Maxima Warringah | H52: 588.6 | I52: 1.04375 | J52: 566 | K52: 3.3875969 | L52: 640 | M52: 1.0189274 | N52: 703 | O52: 3.8819444 | P52: 430.6 | Q52: 1.609697 | R52: 448.6 | S52: 3.792735 | T52: 244 | U52: -0.42015209 | V52: 210.8 | W52: -0.56138161 | X52: 292 | Y52: -0.49022346 | Z52: 326.4 | AA52: -0.24965517 | AB52: 119 | AC52: -0.71325301 | AD52: 636.5 | AE52: -0.27090493 | AF52: 5205.5 | AG52: 0.0097541855
A53: N | D53: L007 | E53: Maxima Chatswood | F53: =E53 -> Maxima Chatswood | H53: 354.55 | I53: 0.76393035 | J53: 310 | K53: 0.8995098 | L53: 456.2 | M53: 0.30716332 | N53: 215 | O53: 0.33044554 | P53: 380 | Q53: 0.60608622 | R53: 202.8 | S53: 0.054054054 | T53: 97 | U53: -0.66459198 | V53: 0 | W53: -1 | X53: 0 | Y53: -1 | Z53: 0 | AA53: -1 | AB53: 0 | AC53: -1 | AD53: 0 | AE53: -1 | AF53: 2015.55 | AG53: 0.0037767839
A54: N | D54: L011 | E54: Maxima Chermside | F54: =E54 -> Maxima Chermside | H54: 802.8 | I54: 0.22080292 | J54: 1168 | K54: 0.82101653 | L54: 913.4 | M54: -0.46102555 | N54: 945.8 | O54: -0.19203827 | P54: 336 | Q54: -0.44481163 | R54: 505.6 | S54: -0.60530835 | T54: 496.4 | U54: -0.55247025 | V54: 305 | W54: -0.75423046 | X54: 636 | Y54: -0.62772185 | Z54: 243 | AA54: -0.81501218 | AB54: 232 | AC54: -0.73779385 | AD54: 816 | AE54: -0.53652164 | AF54: 7400 | AG54: 0.01386629
A55: N | D55: L014 | E55: Maxima Macquarie Centre | F55: =E55 -> Maxima Macquarie Centre | H55: 209 | I55: -0.16533546 | J55: 246.6 | K55: 15.44 | L55: 250 | M55: -0.24607961 | N55: 236 | O55: 0.31991051 | P55: 139 | Q55: -0.036061026 | R55: 246 | S55: 0.2238806 | T55: 89.8 | U55: -0.54646465 | V55: 135 | W55: -0.25 | X55: 44 | Y55: -0.90666101 | Z55: 0 | AA55: -1 | AB55: 0 | AC55: -1 | AD55: 49 | AE55: -0.77625571 | AF55: 1644.4 | AG55: 0.0030813145
A56: N | D56: L015 | E56: Maxima Bondi Junction | F56: =E56 -> Maxima Bondi Junction | H56: 236 | I56: 0.36890951 | J56: 392 | K56: 0.7383592 | L56: 206 | M56: -0.27719298 | N56: 80 | O56: -0.47368421 | P56: 25.8 | Q56: -0.85155351 | R56: 202.8 | S56: -0.14861461 | T56: 313 | U56: 0.24900239 | V56: 298 | W56: -0.21743697 | X56: 488.2 | Y56: -0.26431585 | Z56: 105 | AA56: -0.83306836 | AB56: 33 | AC56: -0.86904762 | AD56: 65 | AE56: -0.29956897 | AF56: 2444.8 | AG56: 0.0045811224
A57: N | D57: L016 | E57: Maxima Joondalup | F57: =E57 -> Maxima Joondalup | H57: 1105.4 | I57: 1.4641106 | J57: 931 | K57: 1.3810742 | L57: 901.15 | M57: 0.69708098 | N57: 683.8 | O57: 0.19420189 | P57: 549 | Q57: 1.750501 | R57: 898.2 | S57: 0.86116867 | T57: 1185 | U57: 0.97565855 | V57: 688.8 | W57: 0.3095057 | X57: 662.6 | Y57: -0.0051051051 | Z57: 587 | AA57: 0.30866124 | AB57: 595.75 | AC57: -0.41844006 | AD57: 1318.4 | AE57: -0.050827934 | AF57: 10106.1 | AG57: 0.018937042
A58: N | D58: L017 | E58: Maxima Burwood | F58: =E58 -> Maxima Burwood | H58: 0 | I58: -1 | J58: 0 | K58: -1 | L58: 0 | M58: -1 | N58: 0 | O58: -1 | P58: 0 | Q58: -1 | R58: 0 | S58: -1 | T58: 0 | U58: 0 | V58: 0 | W58: 0 | X58: 0 | Y58: 0 | Z58: 0 | AA58: 0 | AB58: 0 | AC58: 0 | AD58: 0 | AE58: 0 | AF58: 0 | AG58: 0
A59: N | D59: L018 | E59: Maxima Miranda | F59: =E59 -> Maxima Miranda | H59: 707 | I59: 34.35 | J59: 517 | K59: 3.9238095 | L59: 607 | M59: 1.6693052 | N59: 564 | O59: 5.7142857 | P59: 268 | Q59: 13.888889 | R59: 559.2 | S59: 0.57255343 | T59: 258.8 | U59: -0.22561341 | V59: 198 | W59: -0.53058321 | X59: 100 | Y59: 0.85185185 | Z59: 0 | AA59: -1 | AB59: 0 | AC59: -1 | AD59: 62 | AE59: -0.82995063 | AF59: 3841 | AG59: 0.0071973541
A60: N | D60: L019 | E60: Maxima Liverpool | F60: =E60 -> Maxima Liverpool | H60: 265 | I60: 2.1176471 | J60: 42 | K60: -0.50588235 | L60: 0 | M60: -1 | N60: 0 | O60: -1 | P60: 0 | Q60: -1 | R60: 0 | S60: -1 | T60: 0 | U60: -1 | V60: 0 | W60: -1 | X60: 0 | Y60: -1 | Z60: 0 | AA60: -1 | AB60: 0 | AC60: -1 | AD60: 0 | AE60: -1 | AF60: 307 | AG60: 0.00057526366
A61: N | D61: L021 | E61: Maxima Brisbane Airport | F61: =E61 -> Maxima Brisbane Airport | H61: 21 | I61: -0.7375 | J61: 0 | K61: -1 | L61: 0 | M61: -1 | N61: 0 | O61: -1 | P61: 0 | Q61: -1 | R61: 60 | S61: -0.37238494 | T61: 0 | U61: -1 | V61: 0 | W61: -1 | X61: 0 | Y61: -1 | Z61: 9 | AA61: -0.87919463 | AB61: 15 | AC61: -0.72222222 | AD61: 0 | AE61: 0 | AF61: 105 | AG61: 0.00019675141
... A85: N | D85: L111 | E85: Maxima Botany Town Centre | F85: =E85 -> Maxima Botany Town Centre | H85: 106.94 | I85: -0.19363595 | J85: 183.15 | K85: -0.3089983 | L85: 464.9 | M85: 0.68313964 | N85: 427.77 | O85: 1.2415112 | P85: 364.27 | Q85: 1.7779303 | R85: 297.37 | S85: -0.091611681 | T85: 340.17 | U85: -0.017814864 | V85: 277.59 | W85: -0.2338752 | X85: 309 | Y85: -0.24828492 | Z85: 30.53 | AA85: -0.91113116 | AB85: 156.35 | AC85: -0.34021184 | AD85: 210.94 | AE85: -0.56381307 | AF85: 3168.98 | AG85: 0.0059381076
A86: 1 | D86: Maxima Stores Brand | E86: Maxima Stores Brand | F86: =E86 -> Maxima Stores Brand | H86: 17272.8 | I86: 0.23429159 | J86: 14399.61 | K86: 0.3042428 | L86: 14744.53 | M86: -0.15797412 | N86: 14021.25 | O86: -0.034458229 | P86: 10553.99 | Q86: 0.13553972 | R86: 13839.28 | S86: -0.15357898 | T86: 12609.73 | U86: -0.2208126 | V86: 10210.58 | W86: -0.3407357 | X86: 10521.89 | Y86: -0.46330442 | Z86: 6384.36 | AA86: -0.6346596 | AB86: 6462.7 | AC86: -0.47750322 | AD86: 15552.24 | AE86: -0.36650057 | AF86: 146572.96 | AG86: 0.27465178
A87: N | D87: L046 | E87: Mecca Bondi | F87: =E87 -> Mecca Bondi | H87: 46 | I87: -0.78095238 | J87: 0 | K87: -1 | L87: 0 | M87: -1 | N87: 0 | O87: -1 | P87: 5 | Q87: -0.92424242 | R87: 0 | S87: -1 | T87: 64 | U87: 1.1333333 | V87: 15.6 | W87: -0.35 | X87: 44 | Y87: 2.3846154 | Z87: 18 | AA87: -0.56097561 | AB87: 14.4 | AC87: -0.78571429 | AD87: 0 | AE87: -1 | AF87: 207 | AG87: 0.00038788136
A88: N | D88: L054 | E88: Mecca Rundle Mall | F88: =E88 -> Mecca Rundle Mall | H88: 1135.4 | I88: 0.67167256 | J88: 1034.8 | K88: -0.12062885 | L88: 1078.4 | M88: -0.32150497 | N88: 763 | O88: -0.49663544 | P88: 471.8 | Q88: -0.37343958 | R88: 558.8 | S88: -0.60368794 | T88: 811 | U88: -0.37644164 | V88: 713.6 | W88: -0.20303775 | X88: 1402.4 | Y88: -0.23964433 | Z88: 711.8 | AA88: -0.5498925 | AB88: 445.4 | AC88: -0.66795885 | AD88: 820.4 | AE88: -0.76122009 | AF88: 9946.8 | AG88: 0.018638542
A89: N | D89: L055 | E89: Mecca Chatswood old | F89: =E89 -> Mecca Chatswood old | H89: 0 | I89: -1 | J89: 0 | K89: -1 | L89: 0 | M89: -1 | N89: 0 | O89: 0 | P89: 0 | Q89: 0 | R89: 0 | S89: 0 | T89: 0 | U89: 0 | V89: 0 | W89: 0 | X89: 0 | Y89: 0 | Z89: 0 | AA89: 0 | AB89: 0 | AC89: 0 | AD89: 0 | AE89: 0 | AF89: 0 | AG89: 0
A90: N | D90: L057 | E90: Mecca Narellan | F90: =E90 -> Mecca Narellan | H90: 422.8 | I90: 1.4870588 | J90: 407.8 | K90: 0.58677043 | L90: 332.8 | M90: -0.17745922 | N90: 267 | O90: 0.16086957 | P90: 101 | Q90: -0.53066914 | R90: 108 | S90: -0.76863753 | T90: 18 | U90: -0.92091388 | V90: 12 | W90: -0.96828753 | X90: 0 | Y90: -1 | Z90: 14 | AA90: -0.95870206 | AB90: 28 | AC90: -0.91222571 | AD90: 14 | AE90: -0.98271605 | AF90: 1725.4 | AG90: 0.0032330942
A91: N | D91: L059 | E91: Mecca Booragoon POP | F91: =E91 -> Mecca Booragoon POP | H91: 0 | I91: -1 | J91: 0 | K91: -1 | L91: 0 | M91: -1 | N91: 0 | O91: -1 | P91: 0 | Q91: 0 | R91: 0 | S91: 0 | T91: 0 | U91: 0 | V91: 0 | W91: 0 | X91: 0 | Y91: 0 | Z91: 0 | AA91: 0 | AB91: 0 | AC91: 0 | AD91: 0 | AE91: 0 | AF91: 0 | AG91: 0
A92: N | D92: L060 | E92: Mecca The Glen | F92: =E92 -> Mecca The Glen | H92: 182.8 | I92: -0.095049505 | J92: 229 | K92: 1.4309979 | L92: 188 | M92: -0.40880503 | N92: 188 | O92: 0.93814433 | P92: 43 | Q92: -0.56565657 | R92: 165 | S92: -0.13340336 | T92: 61 | U92: -0.68393782 | V92: 124 | W92: 0 | X92: 148 | Y92: -0.075 | Z92: 101 | AA92: -0.57916667 | AB92: 45 | AC92: 0.66666667 | AD92: 59 | AE92: -0.81677019 | AF92: 1533.8 | AG92: 0.0028740697
A93: N | D93: L061 | E93: Mecca Forrest Chase Pop | F93: =E93 -> Mecca Forrest Chase Pop | H93: 168.6 | I93: 32.72 | J93: 40.6 | K93: 0 | L93: 53 | M93: -0.85963983 | N93: 31 | O93: -0.78014184 | P93: 0 | Q93: -1 | R93: 13.8 | S93: -0.9742921 | T93: 31 | U93: -0.9285385 | V93: 123.6 | W93: -0.47759932 | X93: 24 | Y93: -0.64179104 | Z93: 37.6 | AA93: -0.1826087 | AB93: 6 | AC93: -0.92771084 | AD93: 54 | AE93: -0.59641256 | AF93: 583.2 | AG93: 0.0010928136
A94: N | D94: L062 | E94: Mecca Sunshine Plaza (OLD) | F94: =E94 -> Mecca Sunshine Plaza (OLD) | H94: 491.8 | I94: 1.1799645 | J94: 368.6 | K94: 6.1712062 | L94: 416.8 | M94: 0.32823454 | N94: 281 | O94: -0.31895298 | P94: 290 | Q94: 4.5769231 | R94: 131 | S94: -0.76548514 | T94: 137 | U94: -0.73073899 | V94: 0 | W94: -1 | X94: 0 | Y94: -1 | Z94: 0 | AA94: -1 | AB94: 0 | AC94: -1 | AD94: 0 | AE94: -1 | AF94: 2116.2 | AG94: 0.0039653842
A95: N | D95: L063 | E95: Mecca Fountain Gate | F95: =E95 -> Mecca Fountain Gate | H95: 959.8 | I95: 2.4401434 | J95: 436 | K95: 0.70980392 | L95: 1360.6 | M95: 1.5177646 | N95: 1217.6 | O95: 1.1459288 | P95: 924 | Q95: 0.51326564 | R95: 873 | S95: -0.2465044 | T95: 699.8 | U95: -0.35904012 | V95: 470 | W95: -0.55710516 | X95: 307 | Y95: -0.75420336 | Z95: 400.4 | AA95: -0.62119205 | AB95: 14 | AC95: -0.96846847 | AD95: 541.8 | AE95: -0.60452555 | AF95: 8204 | AG95: 0.015372844
A96: N | D96: L064 | E96: Mecca Southland | F96: =E96 -> Mecca Southland | H96: 1147 | I96: 0.6892489 | J96: 583 | K96: 0.29555556 | L96: 624.8 | M96: 0.098066784 | N96: 423 | O96: -0.19642857 | P96: 456 | Q96: -0.070525887 | R96: 414 | S96: -0.51905204 | T96: 424.8 | U96: -0.54234001 | V96: 300.8 | W96: -0.6291456 | X96: 42 | Y96: -0.95375468 | Z96: 133 | AA96: -0.53658537 | AB96: 143 | AC96: -0.82165128 | AD96: 600 | AE96: -0.71070395 | AF96: 5291.4 | AG96: 0.0099151469
A97: N | D97: L065 | E97: Mecca Kotara | F97: =E97 -> Mecca Kotara | H97: 246 | I97: 0.52795031 | J97: 144 | K97: 3.9655172 | L97: 175 | M97: 3.375 | N97: 112 | O97: 0.43589744 | P97: 0 | Q97: -1 | R97: 236 | S97: 0.60544218 | T97: 167.8 | U97: -0.092972973 | V97: 49 | W97: 0.088888889 | X97: 52 | Y97: -0.50286807 | Z97: 0 | AA97: -1 | AB97: 40 | AC97: -0.047619048 | AD97: 204 | AE97: 0.58139535 | AF97: 1425.8 | AG97: 0.0026716968
A98: N | D98: L066 | E98: Mecca Parramatta | F98: =E98 -> Mecca Parramatta | H98: 951 | I98: 0.096632841 | J98: 957 | K98: 0.26386688 | L98: 1175.8 | M98: 1.0391953 | N98: 1207.8 | O98: 2.0331492 | P98: 632.6 | Q98: 0.14435601 | R98: 812.2 | S98: -0.052275379 | T98: 559 | U98: -0.31259223 | V98: 562.8 | W98: -0.13442018 | X98: 422.8 | Y98: -0.62951279 | Z98: 1004 | AA98: 0.028899365 | AB98: 302 | AC98: -0.55912409 | AD98: 1042 | AE98: -0.20006142 | AF98: 9629 | AG98: 0.018043041
... A160: N | D160: L999 | E160: Event 1 POP | F160: =E160 -> Event 1 POP | H160: 0 | I160: 0 | J160: 0 | K160: 0 | L160: 0 | M160: 0 | N160: 7.8 | O160: 0 | P160: 0 | Q160: 0 | R160: 0 | S160: 0 | T160: 0 | U160: 0 | V160: 0 | W160: 0 | X160: 0 | Y160: 0 | Z160: 0 | AA160: 0 | AB160: 0 | AC160: 0 | AD160: 0 | AE160: 0 | AF160: 7.8 | AG160: 1.4615819e-05
A161: 1 | D161: Mecca Stores Brand | E161: Mecca Stores Brand | F161: =E161 -> Mecca Stores Brand | H161: 29761.58 | I161: 0.97703283 | J161: 24532.76 | K161: 0.71432844 | L161: 27571.46 | M161: 0.37453736 | N161: 24013.93 | O161: 0.42925852 | P161: 19009.59 | Q161: 0.69861793 | R161: 24582.28 | S161: 0.08308157 | T161: 22441.35 | U161: 0.0096232361 | V161: 17962.7 | W161: -0.1012642 | X161: 21366.55 | Y161: -0.27453664 | Z161: 17165.58 | AA161: -0.36882479 | AB161: 15232.48 | AC161: -0.30968518 | AD161: 37117.13 | AE161: -0.25701502 | AF161: 280757.39 | AG161: 0.52608965
A162: N | D162: M010 | E162: Internet Mail Order | F162: =E162 -> Internet Mail Order | H162: 5984.6 | I162: 0.49757269 | J162: 5207.6 | K162: 0.33782048 | L162: 5103 | M162: -0.066649596 | N162: 3743.2 | O162: -0.040598729 | P162: 6642.6 | Q162: 0.85516394 | R162: 4368.6 | S162: -0.26086221 | T162: 9890.2 | U162: 0.44724751 | V162: 6468.8 | W162: 0.22149628 | X162: 6396 | Y162: 0.17375028 | Z162: 8623.4 | AA162: 0.46721339 | AB162: 7025.25 | AC162: 0.17928725 | AD162: 11277.8 | AE162: 0.46510601 | AF162: 80731.05 | AG162: 0.1512757
A163: N | D163: M110 | E163: New Zealand Online Store | F163: =E163 -> New Zealand Online Store | H163: 1588.4 | I163: 1.6810249 | J163: 1353.33 | K163: 0.89168449 | L163: 1400.78 | M163: 0.84254972 | N163: 1312.65 | O163: 0.40430927 | P163: 1018.85 | Q163: 0.22673201 | R163: 1099.69 | S163: -0.45405035 | T163: 1942.87 | U163: 0.072525932 | V163: 1956.91 | W163: 0.39806248 | X163: 1681.2 | Y163: -0.011977104 | Z163: 1221.95 | AA163: -0.33865713 | AB163: 1450.51 | AC163: -0.1441005 | AD163: 2556.92 | AE163: 1.1345377 | AF163: 18584.06 | AG163: 0.034823239
A164: N | D164: M908 | E164: Magic Circle | F164: =E164 -> Magic Circle | H164: 0 | I164: 0 | J164: 0 | K164: 0 | L164: 0 | M164: 0 | N164: 0 | O164: 0 | P164: 0 | Q164: 0 | R164: 0 | S164: 0 | T164: 18 | U164: 0 | V164: 0 | W164: 0 | X164: 0 | Y164: 0 | Z164: 0 | AA164: 0 | AB164: 0 | AC164: 0 | AD164: 0 | AE164: -1 | AF164: 18 | AG164: 3.3728814e-05
A165: 1 | D165: Online Stores Brand | E165: Online Stores Brand | F165: =E165 -> Online Stores Brand | H165: 7573 | I165: 0.65037288 | J165: 6560.93 | K165: 0.42380984 | L165: 6503.78 | M165: 0.044341034 | N165: 5055.85 | O165: 0.045389789 | P165: 7661.45 | Q165: 0.73684127 | R165: 5468.29 | S165: -0.30996622 | T165: 11851.07 | U165: 0.37081232 | V165: 8425.71 | W165: 0.25840822 | X165: 8077.2 | Y165: 0.1295551 | Z165: 9845.35 | AA165: 0.27446577 | AB165: 8475.76 | AC165: 0.10766448 | AD165: 13834.72 | AE165: 0.55280892 | AF165: 99333.11 | AG165: 0.18613266
A166: N | D166: L024 | E166: Mecca Myer Chadstone | F166: =E166 -> Mecca Myer Chadstone | H166: 85 | I166: 0.34920635 | J166: 32 | K166: 0.18518519 | L166: 24 | M166: 0.64383562 | N166: 0 | O166: -1 | P166: 0 | Q166: -1 | R166: 28.8 | S166: -0.80273973 | T166: 6 | U166: -0.80645161 | V166: 26 | W166: 0.083333333 | X166: 13 | Y166: 0 | Z166: 0 | AA166: -1 | AB166: 6 | AC166: 0 | AD166: 0 | AE166: -1 | AF166: 220.8 | AG166: 0.00041374011
A167: N | D167: L025 | E167: Mecca Myer Chatswood | F167: =E167 -> Mecca Myer Chatswood | H167: 0 | I167: 0 | J167: 0 | K167: 0 | L167: 0 | M167: -1 | N167: 0 | O167: -1 | P167: 0 | Q167: 0 | R167: 13 | S167: 0 | T167: 13 | U167: 1.1666667 | V167: 0 | W167: 0 | X167: 0 | Y167: -1 | Z167: 0 | AA167: 0 | AB167: 0 | AC167: 0 | AD167: 0 | AE167: -1 | AF167: 26 | AG167: 4.8719398e-05
A168: N | D168: L027 | E168: Mecca Myer Perth | F168: =E168 -> Mecca Myer Perth | H168: 57 | I168: -0.20168067 | J168: 138 | K168: 0.63895487 | L168: 85 | M168: 0.44557823 | N168: 63 | O168: 0.65789474 | P168: 5 | Q168: -0.87179487 | R168: 36 | S168: -0.58041958 | T168: 48 | U168: -0.36842105 | V168: 24 | W168: -0.25 | X168: 6 | Y168: -0.96666667 | Z168: 34 | AA168: -0.61363636 | AB168: 40 | AC168: -0.5 | AD168: 31 | AE168: -0.7862069 | AF168: 567 | AG168: 0.0010624576
A169: 2 | D169: L028 | E169: Myer Melbourne | F169: =E169 -> Myer Melbourne | H169: 707 | I169: 1.1888545 | J169: 610.7 | K169: 0.058405546 | L169: 686 | M169: 1.1833227 | N169: 566.3 | O169: 0.29677124 | P169: 605.8 | Q169: 1.2125639 | R169: 624.6 | S169: 0.10042283 | T169: 448.8 | U169: 0.060992908 | V169: 317.8 | W169: -0.25469043 | X169: 195.8 | Y169: -0.52636672 | Z169: 0 | AA169: -1 | AB169: 0 | AC169: -1 | AD169: 0 | AE169: -1 | AF169: 4762.8 | AG169: 0.0089246441
A170: 2 | D170: L029 | E170: Myer Sydney | F170: =E170 -> Myer Sydney | H170: 95 | I170: -0.32142857 | J170: 18 | K170: -0.51351351 | L170: 130.4 | M170: 1.9502262 | N170: 10 | O170: 0.66666667 | P170: 0 | Q170: -1 | R170: 18 | S170: -0.9546371 | T170: 6 | U170: -0.96875 | V170: 18 | W170: -0.91428571 | X170: 47.4 | Y170: -0.84885204 | Z170: 30 | AA170: -0.82404692 | AB170: 6 | AC170: -0.97979798 | AD170: 68 | AE170: -0.89457364 | AF170: 446.8 | AG170: 0.00083722411
A171: N | D171: L038 | E171: Mecca Myer Warringah | F171: =E171 -> Mecca Myer Warringah | H171: 39 | I171: 0.11428571 | J171: 0 | K171: -1 | L171: 57 | M171: -0.12037037 | N171: 13 | O171: 0 | P171: 11.7 | Q171: -0.55 | R171: 0 | S171: -1 | T171: 36 | U171: -0.076923077 | V171: 18 | W171: -0.78571429 | X171: 0 | Y171: -1 | Z171: 0 | AA171: -1 | AB171: 0 | AC171: -1 | AD171: 0 | AE171: -1 | AF171: 174.7 | AG171: 0.00032735687
A172: N | D172: M034 | E172: Mecca Myer Adelaide | F172: =E172 -> Mecca Myer Adelaide | H172: 0 | I172: 0 | J172: 0 | K172: 0 | L172: 16 | M172: 0 | N172: 0 | O172: 0 | P172: 15 | Q172: 0 | R172: 0 | S172: 0 | T172: 0 | U172: 0 | V172: 0 | W172: 0 | X172: 0 | Y172: 0 | Z172: 0 | AA172: 0 | AB172: 0 | AC172: 0 | AD172: 0 | AE172: 0 | AF172: 31 | AG172: 5.8088512e-05
A173: 1 | D173: SIS Stores Brand | E173: SIS Stores Brand | F173: =E173 -> SIS Stores Brand | H173: 983 | I173: 0.55439595 | J173: 798.7 | K173: 0.086371055 | L173: 998.4 | M173: 0.98647035 | N173: 652.3 | O173: 0.19534543 | P173: 637.5 | Q173: 0.41729658 | R173: 720.4 | S173: -0.41677461 | T173: 557.8 | U173: -0.27275098 | V173: 403.8 | W173: -0.47990726 | X173: 262.2 | Y173: -0.72253968 | Z173: 64 | AA173: -0.91945633 | AB173: 52 | AC173: -0.94725096 | AD173: 99 | AE173: -0.94502138 | AF173: 6229.1 | AG173: 0.011672231
A174: 0 | D174: Brand Stores by Concept | E174: Brand Stores by Concept | F174: =E174 -> Brand Stores by Concept | H174: 55649.38 | I174: 0.6227706 | J174: 46383 | K174: 0.51029493 | L174: 49857.17 | M174: 0.12380169 | N174: 43805.25 | O174: 0.19126192 | P174: 37932.53 | Q174: 0.49579761 | R174: 44727.25 | S174: -0.073579271 | T174: 47543.83 | U174: -0.0072392198 | V174: 37069.79 | W174: -0.13735816 | X174: 40305.82 | Y174: -0.29503248 | Z174: 33501.29 | AA174: -0.37109219 | AB174: 30222.94 | AC174: -0.29832545 | AD174: 66670.09 | AE174: -0.21773217 | AF174: 533668.34 | AG174: 1
B177: Mecca:RPT Item Store Sales Monthly:ARPT1
E179: Currency | F179: Report AUD
E180: Company | F180: Mecca Brands Consolidated
E181: Sales Version | F181: Actual
E182: Lifestage | F182: All Lifestage
E183: DCS | F183: All DCS
E184: Brand | F184: 3MORE
E185: Item | F185: All Item
H188: =H32 -> 2025.M01 | I188: =I32 -> 2025.M01 | J188: =J32 -> 2025.M02 | K188: =K32 -> 2025.M02 | L188: =L32 -> 2025.M03 | M188: =M32 -> 2025.M03 | N188: =N32 -> 2025.M04 | O188: =O32 -> 2025.M04 | ... AF188: =AF32 -> YTD 2025.M12
H189: Total Stores by Concept Excl Non Store | I189: Total Stores by Concept Excl Non Store | J189: Total Stores by Concept Excl Non Store | K189: Total Stores by Concept Excl Non Store | L189: Total Stores by Concept Excl Non Store | M189: Total Stores by Concept Excl Non Store | N189: Total Stores by Concept Excl Non Store | O189: Total Stores by Concept Excl Non Store | P189: Total Stores by Concept Excl Non Store | Q189: Total Stores by Concept Excl Non Store | R189: Total Stores by Concept Excl Non Store | S189: Total Stores by Concept Excl Non Store | T189: Total Stores by Concept Excl Non Store | U189: Total Stores by Concept Excl Non Store | V189: Total Stores by Concept Excl Non Store | W189: Total Stores by Concept Excl Non Store | X189: Total Stores by Concept Excl Non Store | Y189: Total Stores by Concept Excl Non Store | Z189: Total Stores by Concept Excl Non Store | AA189: Total Stores by Concept Excl Non Store | AB189: Total Stores by Concept Excl Non Store | AC189: Total Stores by Concept Excl Non Store | AD189: Total Stores by Concept Excl Non Store | AE189: Total Stores by Concept Excl Non Store | AF189: Total Stores by Concept Excl Non Store
D190: YTD STORE SALES BY CONCEPT | AF190: =$I$25&" "&$E$26 -> December 2025
H191: JAN 2025 | J191: FEB 2025 | L191: MAR 2025 | N191: APR 2025 | P191: MAY 2025 | R191: JUN 2025 | T191: JUL 2025 | V191: AUG 2025 | X191: SEP 2025 | Z191: OCT 2025 | AB191: NOV 2025 | AD191: DEC 2025 | AF191: =LEFT(AF188,8) -> YTD 2025
A192: A | F192: COSMETICA | G192: Total Store Sales | I192: 59 | K192: 91 | M192: 39 | O192: 61.92 | Q192: 70 | S192: 117 | U192: 83.88 | W192: 67 | Y192: 77.98 | AA192: 42 | AC192: 0 | AE192: 67 | AF192: 775.78
...
